Workbook
Name ArbMode: Listes!$B$359:$B$365
Name Autom: Listes!$B$410:$B$411
Name BULLET: 'APPENDIX B-2 (FE - USEC&GC)'!$N$13:$N$22
Name BULLET: 'APPENDIX F-1 ISC-US'!$N$13:$N$18
Name BULLET: 'APPENDIX F-2 ISC-USWC'!$N$13:$N$18
Name BULLET: 'APPENDIX B-1 (FE - USWC)'!$N$13:$N$20
Name Charges: Listes!$A$3:$A$230
Name Container: Listes!$B$245:$B$254
Name CST: Listes!$B$434:$B$440
Name CURRENCY: Listes!$B$483:$B$618
Name DAYS: Listes!$B$449:$B$450
Name DDTARIFF: Listes!$B$454:$B$457
Name DDTARIFFUS: Listes!$B$461:$B$463
Name DDTARIFFUSE: Listes!$B$466:$B$467
Name DDTARIFFUSI: Listes!$B$461:$B$463
Name droppull: Listes!$B$292:$B$293
Name EQTYPE: Listes!$B$471:$B$474
Name Equip: Listes!$B$374:$B$397
Name Exceptions: Listes!$H$3:$H$231
Name EXPIMP: Listes!$B$444:$B$445
Name GRIPSS: Listes!$B$368:$B$371
Name GRIPSS_EQ: Listes!$B$415:$B$430
Name Mode: Listes!$B$296:$B$344
Name MQCType: Listes!$B$400:$B$402
Name OLE_LINK1: 'Boiler Plate'!$A$377
Name OOG: Listes!$B$355:$B$356
Name OPREEFER: Listes!$B$478:$B$479
Name Reefer: Listes!$B$258:$B$264
Name SDD: Listes!$B$234:$B$237
Name shipper: Cover!$B$7
Name ShipperCert: Listes!$B$405:$B$406
Name ShipperOwn: Listes!$B$351:$B$352
Name Type_note2: Listes!$B$267:$B$289
Name YesNo: Listes!$B$347:$B$348

Sheet Boiler Plate
A1: =CONCATENATE("AMENDMENT ",Cover!B2," TO SERVICE CONTRACT ",Cover!B1) -> AMENDMENT 58 TO SERVICE CONTRACT 25-3117
A3: =CONCATENATE(" This Amendment to the Service Contract (the “Amendment”) is made as of the date of filing of the Amendment with the Federal Maritime Commission (the “Effective Date”), by and between CMA CGM S.A. (hereinafter referred to as “Carrier”) and ",IF(Cover!B7="","__________",Cover!B7)," (hereinafter referred to as “Merchant”).") -> This Amendment to the Service Contract (the “Amendment”) is made as of the date of filing of the Amendment with the Federal Maritime Commission (the “Effective Date”), by and between CMA CGM S.A. (hereinafter referred to as “Carrier”) and LOGISTIQUE PRIME FREIGHT INC (hereinafter referred to as “Merchant”).
A5: WHEREAS, Carrier and Merchant hereby agree to amend the Contract as defined herein.
A7: NOW THEREFORE, intending to be legally bound Carrier and Merchant hereby agree that this Amendment shall amend the Contract as follows:
A9: Pursuant to the attached Excel document and/or the following revisions:
A11: Section | B11: Heading
A12: Term | B12: Appendix
A13: 6 | B13: B1,B2: Rates
A23: BOTH PARTIES HEREBY AGREE THAT THE REMAINING TERMS AND CONDITIONS OF THE CONTRACT SHALL NOT BE AMENDED BY THIS WRITING AND SHALL REMAIN IN FULL FORCE AND EFFECT FOR THE DURATION OF THE TERM.
A25: IN WITNESS WHEREOF, THE PARTIES HERETO HAVE EXECUTED THIS AMENDMENT TO THE SERVICE CONTRACT, WHICH SHALL BECOME EFFECTIVE AS OF THE DATE OF FILING WITH THE FEDERAL MARITIME COMMISSION.
A27: The individual signing this Amendment on behalf of the Merchant represents and warrants that he or she is empowered and duly authorized to bind the Merchant to this Amendment according to its terms.
A31: ______________________________ | B31: ______________________________
A32: Signature | B32: Signature
A34: Date_________11/12/2025_________ | B34: Date__________________
A35: Charles A. Gender | B35: =IF(Cover!B9="","Name: ________________________",Cover!B9) -> Neil Sabharwal
A36: Sr. Director, Bids and Contracting | B36: =IF(Cover!B10="","Title: _________________________",Cover!B10) -> Managing Director
A37: CMA CGM (America) LLC
A38: As Agents for: | B38: For and on Behalf of:
A39: CMA CGM S.A. | B39: =IF(Cover!B7="","(Merchant)",Cover!B7) -> LOGISTIQUE PRIME FREIGHT INC
A40: CMA CGM S.A.
A42: Service Contract Number: | B42: =Cover!B1 -> 25-3117
A44: Essential Terms (“ET”) Number: | B44: CMDU 037
A48: =CONCATENATE("This Service Contract (“Contract”) will become effective (the “Effective Date”) upon date signed by both parties as required by 46 §CFR 530.8 and will expire on ",IF(Cover!B6="","__________",TEXT(Cover!B6,"mmmmmmmmm dd, yyyy")),".", " In no event shall the Effective Date be earlier than thirty (30) days prior to the filing of the Contract with the Federal Maritime Commission (“FMC”).") -> This Service Contract (“Contract”) will become effective (the “Effective Date”) upon date signed by both parties as required by 46 §CFR 530.8 and will expire on December 31, 2025. In no event shall the Effective Date be earlier than thirty (30) days prior to the filing of the Contract with the Federal Maritime Commission (“FMC”).
A50: =CONCATENATE("This Contract is made by and between CMA CGM S.A., a French company having its registered office at Boulevard Jacques Saadé, 4 Quai d'Arenc, 13235 Marseille CEDEX 02, France (hereinafter referred to as “Carrier”) and ",IF(Cover!B7="","__________",Cover!B7),", (hereinafter referred to as “Merchant”) whereby the parties mutually agree to bind themselves to the terms and conditions set forth herein.") -> This Contract is made by and between CMA CGM S.A., a French company having its registered office at Boulevard Jacques Saadé, 4 Quai d'Arenc, 13235 Marseille CEDEX 02, France (hereinafter referred to as “Carrier”) and LOGISTIQUE PRIME FREIGHT INC, (hereinafter referred to as “Merchant”) whereby the parties mutually agree to bind themselves to the terms and conditions set forth herein.
A52: =CONCATENATE("Pursuant to FMC Regulation 46 C.F.R. §530.6, by execution of this Contract, Merchant certifies its status and that of all of its affiliates authorized to use this Contract as: (1) ",IF(Cover!B19="YES","__X__","_____")," Owner of the Cargo ('Beneficial Cargo Owner' or 'BCO'), (2) ",IF(Cover!B21="YES","__X__","_____")," Non-Vessel Operating Common Carrier (NVOCC), or (3) ",IF(Cover!B20="YES","__X__","_____"), " Shipper's Association",".") -> Pursuant to FMC Regulation 46 C.F.R. §530.6, by execution of this Contract, Merchant certifies its status and that of all of its affiliates authorized to use this Contract as: (1) _____ Owner of the Cargo ('Beneficial Cargo Owner' or 'BCO'), (2) __X__ Non-Vessel Operating Common Carrier (NVOCC), or (3) _____ Shipper's Association.
A54: =IF(Cover!B21="YES",CONCATENATE("For all Merchants certifying their status as a NVOCC, it is further certified that Merchant is a duly licensed and bonded NVOCC having a published tariff and surety bond number ",IF(Cover!B22="","__________",Cover!B22),", dated ",IF(Cover!B23="","__________",TEXT(Cover!B23,"mmmmmmmmm dd, yyyy")),", issued by ",IF(Cover!B24="","__________",Cover!B24)," on ",IF(Cover!F23="",IF(Cover!B23="","__________",TEXT(Cover!B23,"mmmmmmmmm dd, yyyy")),TEXT(Cover!F23,"mmmmmmmmm dd, yyyy")),", which has been filed with the FMC, that an appropriate tariff or tariffs have been filed with the FMC, and that copies of tariff pages have been provided to Carrier."),"") -> For all Merchants certifying their status as a NVOCC, it is further certified that Merchant is a duly licensed and bonded NVOCC having a published tariff and surety bond number KMS52005, dated October 16, 2024, issued by SOUTHWEST MARINE AND GENERAL INSURANCE COMPANY on October 16, 2024, which has been filed with the FMC, that an appropriate tariff or tariffs have been filed with the FMC, and that copies of tariff pages have been provided to Carrier.
A56: As legally required, Carrier’s Bill of Lading, Merchant’s statement of containers shipped under this Contract, written communications issued by Carrier regarding such statement, and force majeure correspondence and notices, shall constitute the records supporting performance under this Contract, and shall be maintained by Carrier’s designated agent in the United States of America at the following address:
A58: CMA CGM (America) LLC 1 CMA CGM Way, Norfolk, Virginia 23502 Phone: (757) 961-2100
A60: In witness whereof, the parties hereby agree to ratify any electronic signatures and be bound by the terms and conditions of this Contract by signature of their duly authorized representatives, set forth below.
A62: The individual signing this Contract on behalf of the Merchant represents and warrants that he or she is empowered and duly authorized to bind the Merchant to this Contract according to its terms.
A66: ______________________________ | B66: ______________________________
A67: Signature | B67: Signature
A69: Date ___________1/31/2025______________ | B69: Date ___________2/7/2025______________
A70: Charles A. Gender | B70: =IF(Cover!B9="","Contact:",Cover!B9) -> Neil Sabharwal
A71: Sr. Director, Bids and Contracting | B71: =IF(Cover!B10="","Title:",Cover!B10) -> Managing Director
A73: For and on behalf of: | B73: For and on behalf of:
A74: CMA CGM (America) LLC
A75: As agents for:
A76: CMA CGM S.A. | B76: =IF(Cover!B7="","",Cover!B7) -> LOGISTIQUE PRIME FREIGHT INC
A77: 1 CMA CGM Way | B77: =IF(Cover!B11="","",Cover!B11) -> 4 PLACE DU COMMERCE SUITE 230, QUEBEC
A78: Norfolk, VA 23502 USA | B78: =IF(Cover!B12="","",Cover!B12) -> Montreal, Canada. H3E1J4.
A80: Tel: (757) 961-2100 | B80: =IF(Cover!B14="","Tel: (required)",CONCATENATE("Tel: ",Cover!B14)) -> Tel: 5146555430
A81: Email: usa.contracts@usa.cma-cgm.com | B81: =IF(Cover!B16="","Email: (required)",CONCATENATE("Email: ",Cover!B16)) -> Email: neil@primefreight.com
A83: 1. APPLICATION OF CONTRACT
A85: A. This Contract applies with respect to the transportation of Merchant's and its Affiliates’ (as defined herein) commodities (the “Cargo”) listed in one or more appendices attached hereto (the "Appendix" or “Appendices”) between the origin and destination locations listed in any Appendix. This Contract, its Appendices and exhibits thereto, together with the terms and conditions of Carrier’s standard form bill of lading (including sea waybills, the “Bill of Lading”), Carrier’s governing tariff(s) and the Carrier’s standard credit terms (if applicable), each as in effect on the date the Cargo is received, embody the entire understanding between the parties. There are no other agreements, understandings, conditions, warranties or representations, oral or written, express or implied, with reference to the subject matter of this Contract, which are integrated herein. No modification of this Contract or waiver of any of its terms or conditions shall be of any force or effect unless made in a writing signed by both parties. In the event of any conflict among the terms and conditions of this Contract, the Bill of Lading and the Carrier’s applicable tariff(s), the order of governance shall be, first, the Bill of Lading, second, this Contract, and third, the tariff(s).
A87: B. Notwithstanding anything to the contrary contained herein, Carrier shall not be liable or responsible to the Merchant or its Affiliates for any consequential, incidental, special, or punitive damages, or for loss of profits or revenues incurred by Merchant or its affiliates that arise out of or relate to this Contract or any booking. The Carrier does not undertake that the Goods or Containers or other packages shall arrive at the port of discharge or place of delivery at any particular time or to meet any particular market or use, and the Carrier shall in no circumstances be liable for any direct, indirect or consequential loss or damage caused by delay or any other cause.
A89: C. For purposes of determining whether a shipment is made during the term of this Contract, the date when the Cargo is received by Carrier, its sub-contractor, or agent shall govern. Cargo shall not be considered as “received” until the full Bill of Lading quantity has been received by Carrier, its sub-contractor or agent. Carrier's duties and responsibilities under this Contract shall commence when Carrier, its sub-contractor, or agent takes possession and control of Merchant's Cargo or and shall end when Carrier, its sub-contractor, or agent delivers Merchant's Cargo at the port or place of delivery designated on the Bill of Lading or imposed by specific circumstances.
A92: 2. MERCHANT
A94: A. The term “Merchant” means the entity signing this Contract and its affiliates and subsidiaries named on the signature page thereof or listed in any Appendix to this Contract (the “Affiliates”). The person signing this Contract on behalf of Merchant warrants and represents that he or she has authority to enter into this Contract on behalf of Merchant and its Affiliates.
A96: B. Merchant, whether a BCO, NVOCC, Shipper's Association, or other entity, is entering into this Contract as an independent contractor and in no event shall be considered an agent of Carrier, either under this Contract or Carrier’s Bill of Lading. Notwithstanding anything to the contrary, Merchant signing the Contract remains fully responsible for the complete performance of this Contract. The Affiliates of Merchant, or any third parties entitled to use the Contract, shall be jointly and severally liable for the said performance.
A98: C. In the event Merchant certifies itself as an NVOCC and subsequently its license, tariff, and/or bond is suspended or cancelled, Carrier may unilaterally terminate this Contract with immediate effect upon written notice to Merchant. Alternatively, and in its sole discretion, Carrier may by written notice to Merchant suspend performance of the Contract until such time as Merchant demonstrates to Carrier’s satisfaction that Merchant meets all Shipping Act and FMC licensing, tariff, and financial responsibility requirements. In the event Carrier elects to terminate this Contract or suspend performance as provided under this paragraph, the Merchant’s MQC shall be reduced either i) in proportion to the amount of time remaining before the expiration of the Contract or, ii) in proportion to the duration of the suspension.
A100: 3. MERCHANT’S AFFILIATES
A102: A. Merchant warrants and represents that all entities identified as Affiliates are under at least 50% common ownership or control by reason of being a parent and subsidiary or entities associated with, under common control with, or otherwise related to Merchant through common stock ownership or common directors or officers. Merchant will provide reasonable evidence to prove common ownership or control of the Affiliates, upon request of Carrier.
A104: B. For a Merchant certifying as a Shipper's Association, all members entitled to use this Contract must be listed in the Affiliate Appendix attached hereto.
A106: 4. MERCHANT’S MINIMUM QUANTITY COMMITMENT
... A331: TERM 102 ELECTRONIC ENDORSEMENT
B332: =CONCATENATE(Cover!B1&"-"&Cover!B2) -> 25-3117-58
A333: Carrier will accept an Electronic Signature (a digital copy of a signature in place of a handwritten signature) or Electronic Endorsement (email acknowledgment and acceptance) in substitution of an original “pen and ink” endorsement on approved Service Contracts (including amendments).
A334: Merchant may identify persons authorized to submit Electronic Signature or Electronic Endorsement for Service Contracts, including the authorized person’s full name, title, electronic mail address and telephone number. Unless Merchant identifies specific individuals authorized to approve Service Contracts, any individual who purports to be a representative of the Merchant may accept the Contract on behalf of the Merchant and in doing so represents and warrants that he or she is empowered and duly authorized to bind the Merchant to the Service Contract, according to its terms.
A336: Merchant must notify the Carrier in writing if it does not authorize any of its representatives to use Electronic Signature or Electronic Endorsement.
A338: Name, Title, Phone, Electronic Mail Address
A339: Name: Title: Phone: Email:
A343: Name: Title: Phone: Email:
A347: Name: Title: Phone: Email:
A351: Name: Title: Phone: Email:
A357: Credit Addendum
A359: During the term of this Contract, Carrier shall grant to Merchant credit for Freight charges. For the purposes of this Credit Addendum, the term “Freight” excludes taxes, duties, customs fines/outlays, demurrage, storage beyond free time, interest, court fees, attorney fees and other disbursements incurred in relation to the execution of Carrier’s rights under the Contract, if any, which are not subject to credit terms. Merchant shall pay all amounts due per Carrier’s invoice for each (export and/or import) shipment within 30 calendar days from the date of Carrier’s invoice (the “Due Date”). Payment must be made by electronic funds transfer, and no checks will be accepted. In the event of any conflict between any other terms in the Contract and this Credit Addendum, this Credit Addendum shall govern all matters related to Merchant’s payment obligations and the credit facilities granted to Merchant herein.
A361: Beneficiaries
A362: Credit shall be extended solely to the Merchant named herein and to its named Affiliates listed in the Affiliates Appendix to the Contract. Merchant shall be jointly and severally liable with its Affiliates for the full payment of Carrier’s invoices, which shall not be subject to offset or other deduction. Merchant’s guarantee of payment shall remain valid even if its named Affiliate has been sold or become bankrupt or insolvent. Credit shall not apply to any Affiliates that are not named in the Affiliates Appendix, and any request to add an Affiliate to this Contract shall be subject to Carrier’s prior written approval.
... A371: In the event of an invoice not being paid by the Due Date, the Carrier may suspend credit. Such suspension shall be notified to the Merchant in writing and shall be immediately applicable to any services under performance. Additionally, credit may be terminated by the Carrier at any time subject to thirty (30) days prior written notice to the Merchant. Carrier may terminate credit with immediate effect upon occurrence of either (i) default or breach of any terms of this Credit Addendum by the Merchant or one of its listed Affiliates, (ii) liquidation, bankruptcy, insolvency, credit protection proceedings involving them. Upon the termination of credit becoming effective, all sums outstanding thereunder shall become immediately due and payable.

Sheet Cover
A1: Service Contract #: | B1: 25-3117
A2: Amendment #: | B2: 58
A3: Effective Date of Amendment: | B3: 45974
A4: Term 4 MQC: | B4: =MQC!E8 -> 150 | C4: TEUS
A5: Term 8 Contract Effective Date: | B5: 45703
A6: Term 8 Contract Expiration Date: | B6: 46022
A7: Term 2 Merchant Name: | B7: LOGISTIQUE PRIME FREIGHT INC
A8: Partner Code: | B8: 0004563721
A9: 41 Contact Person: | B9: Neil Sabharwal
A10: Title: | B10: Managing Director
A11: Address: | B11: 4 PLACE DU COMMERCE SUITE 230, QUEBEC
B12: Montreal, Canada. H3E1J4.
A14: Phone: | B14: 5146555430
A15: Fax:
A16: Email: | B16: neil@primefreight.com
A17: SVI:
A18: Term 10 Merchant Certification: | B18: You must indicate one of the following as (YES)
A19: Owner of the Cargo (BCO)
A20: Shippers Association
A21: NVOCC | B21: YES
A22: If NVOCC, provide Bond Number: | B22: KMS52005
A23: If NVOCC, provide Bond date | B23: 45581
A24: If NVOCC provide the name of the Bonding Company | B24: SOUTHWEST MARINE AND GENERAL INSURANCE COMPANY
A25: If NVOCC resides in the USA, provide FMC License Number: Or If NVOCC resides outside the USA, provide FMC Organization Number: | B25: 034170
A26: If NVOCC, Shipper Certifies to Carrier that they are an Ocean Transportation Intermediary (OTI) performing NVOCC Services. OTI License and Bond are on file with the FMC.
A27: Term 100 Tariff(s) of General Applicability: | B27: CMDU 020, 100, 102 , 043 , 029
A29: Term 101 Free Time Exceptions:
A30: A - Demurrage / B - Detention | B30: Per Tariff(s) unless specified in Appendix "Term 101 FREE TIME Exceptions"
A31: CMA-CGM Sales Representative: | B31: DU Shuang
B32: cda.sdu@usa.cma-cgm.com
A33: Table of Contents
A34: CMDU#044 | B34: A-1 | C34: OUTBOUND FAR EAST (USWC-ASIA) | E34: =A34 -> CMDU#044
A35: CMDU#044 | B35: A-2 | C35: OUTBOUND FAR EAST (USEC&USGC-ASIA) | E35: =A35 -> CMDU#044
A36: CMDU#043 B1 | B36: B-1 | C36: INBOUND FAR EAST (ASIA-USWC) | E36: =A36 -> CMDU#043 B1
A37: CMDU#043 B2 | B37: B-2 | C37: INBOUND FAR EAST (ASIA-USEC & USGC) | E37: =A37 -> CMDU#043 B2
A38: CMDU#028 | B38: C-1 | C38: OUTBOUND (USA-MEDITERRANEAN) | E38: =A38 -> CMDU#028
A39: CMDU#028 | B39: C-2 | C39: OUTBOUND (USA-ARABIAN GULF & RED SEA) | E39: =A39 -> CMDU#028
A40: CMDU#028 | B40: C-3 | C40: OUTBOUND (USWC-ARABIAN GULF) | E40: =A40 -> CMDU#028
A41: CMDU#028 | B41: C-5 | C41: OUTBOUND (USA-E & W AFRICA) | E41: =A41 -> CMDU#028
A42: CMDU#029 D1 | B42: D-1 | C42: INBOUND (MEDITERRANEAN-USA EC & GC) (AMERIGO) | E42: =A42 -> CMDU#029 D1
A43: CMDU#029 D2 | B43: D-2 | C43: INBOUND (MEDITERRANEAN-USA WC) (TPX) | E43: =A43 -> CMDU#029 D2
A44: CMDU#029 D4 | B44: D-4 | C44: INBOUND (MEDITERRANEAN-USVI/PR) | E44: =A44 -> CMDU#029 D4
A45: CMDU#029 D5 | B45: D-5 | C45: INBOUND (E & W AFRICA-USA)
A46: CMDU#028 | B46: E-1 | C46: OUTBOUND (USA-USEC USGC-INDIAN SUB. CONTINENT) (INDAMEX) | E46: =A46 -> CMDU#028
A47: CMDU#028 | B47: E-2 | C47: OUTBOUND (USWC-ISC) | E47: =A47 -> CMDU#028
A48: CMDU#029 F1 | B48: F-1 | C48: INBOUND (INDIAN SUB. CONTINENT-USA EC) (INDAMEX) | E48: =A48 -> CMDU#029 F1
A49: CMDU#029 F2 | B49: F-2 | C49: INBOUND (INDIAN SUB. CONTINENT-USA WC ) (TPX) | E49: =A49 -> CMDU#029 F2
A50: CMDU#029 F3 | B50: F-3 | C50: INBOUND (INDIAN SUB. CONTINENT-USVI/PR) | E50: =A50 -> CMDU#029 F3
A51: CMDU#091 | B51: G-1 | C51: OUTBOUND (USA-TRANSAT) | E51: =A51 -> CMDU#091
A52: CMDU#090 H1 | B52: H-1 | C52: INBOUND (NE - US) (TRANSAT) | E52: =A52 -> CMDU#090 H1
A53: CMDU#090 H2 | B53: H-2 | C53: INBOUND (NE-USWC)-(TPX) | E53: =A53 -> CMDU#090 H2
A54: CMDU#044 | B54: I-1 | C54: US WEST COAST-AUSTRALIA/NEW ZEALAND | E54: =A54 -> CMDU#044
A55: CMDU#101 | B55: I-2 | C55: US EAST COAST-AUSTRALIA/NEW ZEALAND/SOUTH PACIFIC ISLANDS | E55: =A55 -> CMDU#101
A56: CMDU#043 J1 | B56: J-1 | C56: AUSTRALIA/NEW ZEALAND/FRENCH POLYNESIAN ISLAND/ PAPOUASIA/NEW GUINEA- USA USWC/USEC (RTW) | E56: =A56 -> CMDU#043 J1
A57: CMDU#043 N1 | B57: N-1 | C57: CARIBBEAN (PEX 2) | E57: =A57 -> CMDU#043 N1
A58: CMDU#005 P-1 | B58: P-1 | C58: OUTBOUND USA TO CARIB-LATIN AMER
A59: CMDU#006 P-2 | B59: P-2 | C59: INBOUND CARIB-LATIN AMER TO USA
A60: CMDU#007 P-3 | B60: P-3 | C60: OUTBOUND PUERTO RICO & US V.I. TO LATAM
A61: CMDU#007 P-4 | B61: P-4 | C61: INBOUND LATAM TO PUERTO RICO & US V.I.
B62: Affiliates | C62: Affiliates

Sheet MQC
B2: MQC | C2: Appendix | E2: (TEUS)
C3: ALL | E3: 150
C8: Total | E8: =SUM(E3:E6) -> 150
A9: 41

Sheet APPENDIX B-1  (FE - USWC)
A1: Service Contract: | C1: =Cover!B1 -> 25-3117
A2: TERM 6
A3: Amendment Number: | C3: =Cover!B2 -> 58
A4: Merchant Name: | C4: =Cover!B7 -> LOGISTIQUE PRIME FREIGHT INC
A5: Appendix: | C5: B-1
A6: Trade Service: | C6: INBOUND FAR EAST (ASIA-USWC)
A7: TARIFF applicability | C7: CMDU#043 B1
A9: 41 | B9: INB
A11: COMMODITY INDEX
A12: - Unless otherwise indicated, excludes temperature controlled cargo, hazardous cargo, cargo requiring special handling and/or equipment, overweight containers.
A13: FAK/Bullets | B13: Description | J13: Named Account | L13: Partner Code | N13: ALL
A14: FAK PSW | B14: FAK | N14: =IF($A14>0,$A14,"") -> FAK PSW
A15: FAK PNW | B15: FAK | N15: =IF($A15>0,$A15,"") -> FAK PNW
A16: FAK HAWAII | B16: FAK | N16: =IF($A16>0,$A16,"") -> FAK HAWAII
N17: =IF($A17>0,$A17,"")
N18: =IF($A18>0,$A18,"")
N19: =IF($A19>0,$A19,"")
N20: =IF($A20>0,$A20,"")
A21: Port Group Codes
A22: Port Group Codes | B22: Description
A23: BP TW | B23: KAOHSIUNG,TAIPEI
A24: BP VAN | B24: YANTIAN,XIAMEN,NINGBO,SHANGHAI,HONG KONG,SHEKOU
A25: LAX-LGB | B25: LOS ANGELES,LONG BEACH
A26: BP SEA | B26: SHANGHAI,YANTIAN,XIAMEN,NINGBO,SHEKOU,HONG KONG
A27: BP TIW | B27: YANTIAN,SHANGHAI,NINGBO
A28: BP FUJI | B28: TOKYO, NAGOYA, KOBE
A29: BP LAX | B29: NANSHA,YANTIAN,XIAMEN,SHANGHAI,NINGBO,QINGDAO,TIANJINXINGANG
A30: BP OAK | B30: YANTIAN,SHEKOU,SHANGHAI,NINGBO,QINGDAO
A31: SE ASIA BP PSW | B31: PORT KLANG,SINGAPORE,LAEM CHABANG,VUNG TAU,HAIPHONG
A32: BP PRR | B32: SHANGHAI,QINGDAO,TIANJINXINGANG
A33: NCPRC BP OAK | B33: SHANGHAI, NINGBO, QINGDAO
... A36: SPRC BP OAK | B36: YANTIAN, SHEKOU
A41: RATES CONDITIONS
A42: Rates in USD unless otherwise specified. Surcharges listed per line item are exceptions to Note 2 applicability.
A43: For Place of Receipt indicate origin of cargo
A44: For Place of Intermodal Delivery indicate point and state. Mode: PORT=CY, RAIL=R (RAMP), MOTOR=M , RAIL/MOTOR=RM , BARGE=B, RAIL/BARGE=RB (RAMP), MOTOR/BARGE=BM
A45: FAK/ BULLETS | B45: Place of Receipt | C45: POL | D45: POD | E45: Place of Delivery | F45: MODE | G45: SDD (Origin; Dest) | H45: Curr | I45: D20 | J45: D40 | K45: H40 | L45: H45 | X45: Effective date | Y45: Expiration Date | Z45: Note | AA45: IPI Construction
A47: FAK PSW | C47: NCPRC BP LAX | D47: LAX-LGB | F47: CY/CY | G47: N/N | H47: USD | I47: 1785 | J47: 2100 | K47: 2100 | L47: 2660 | Z47: 1,2,4 | AA47: E
A48: FAK PSW | C48: NCPRC BP OAK | D48: OAKLAND, CA | F48: CY/CY | G48: N/N | H48: USD | I48: 1785 | J48: 2100 | K48: 2100 | L48: 2660 | Z48: 1,2,4 | AA48: E
A49: FAK PSW | C49: NCPRC BP LAX | D49: LAX-LGB | E49: CHICAGO, IL | F49: CY/R | G49: N/N | H49: USD | I49: 3870 | J49: 4550 | K49: 4550 | L49: 5760 | Z49: 1,2,4 | AA49: E
A50: FAK PSW | C50: NCPRC BP LAX | D50: LAX-LGB | E50: CINCINNATI, OH | F50: CY/R | G50: N/N | H50: USD | I50: 4380 | J50: 5150 | K50: 5150 | L50: 6520 | Z50: 1,2,4 | AA50: E
A51: FAK PSW | C51: NCPRC BP LAX | D51: LAX-LGB | E51: CLEVELAND, OH | F51: CY/R | G51: N/N | H51: USD | I51: 4380 | J51: 5150 | K51: 5150 | L51: 6520 | Z51: 1,2,4 | AA51: E
A52: FAK PSW | C52: NCPRC BP LAX | D52: LAX-LGB | E52: COLUMBUS, OH | F52: CY/R | G52: N/N | H52: USD | I52: 4380 | J52: 5150 | K52: 5150 | L52: 6520 | Z52: 1,2,4 | AA52: E
A53: FAK PSW | C53: NCPRC BP LAX | D53: LAX-LGB | E53: DALLAS, TX | F53: CY/R | G53: N/N | H53: USD | I53: 3870 | J53: 4550 | K53: 4550 | L53: 5760 | Z53: 1,2,4 | AA53: E
A54: FAK PSW | C54: NCPRC BP LAX | D54: LAX-LGB | E54: DENVER, CO | F54: CY/R | G54: N/N | H54: USD | I54: 4550 | J54: 5350 | K54: 5350 | L54: 6775 | Z54: 1,2,4 | AA54: E
A55: FAK PSW | C55: NCPRC BP LAX | D55: LAX-LGB | E55: DETROIT, MI | F55: CY/R | G55: N/N | H55: USD | I55: 4720 | J55: 5550 | K55: 5550 | L55: 7025 | Z55: 1,2,4 | AA55: E
A56: FAK PSW | C56: NCPRC BP LAX | D56: LAX-LGB | E56: EL PASO, TX | F56: CY/R | G56: N/N | H56: USD | I56: 4125 | J56: 4850 | K56: 4850 | L56: 6140 | Z56: 1,2,4 | AA56: E
A57: FAK PSW | C57: NCPRC BP LAX | D57: LAX-LGB | E57: HOUSTON, TX | F57: CY/R | G57: N/N | H57: USD | I57: 4210 | J57: 4950 | K57: 4950 | L57: 6265 | Z57: 1,2,4 | AA57: E
A58: FAK PSW | C58: NCPRC BP LAX | D58: LAX-LGB | E58: INDIANAPOLIS, IN | F58: CY/RM | G58: N/Y | H58: USD | I58: 6420 | J58: 7550 | K58: 7550 | L58: 9560 | Z58: 1,2,4 | AA58: E
A59: FAK PSW | C59: NCPRC BP LAX | D59: LAX-LGB | E59: KANSAS CITY, KS | F59: CY/R | G59: N/N | H59: USD | I59: 3870 | J59: 4550 | K59: 4550 | L59: 5760 | Z59: 1,2,4 | AA59: E
A60: FAK PSW | C60: NCPRC BP LAX | D60: LAX-LGB | E60: LOUISVILLE, KY | F60: CY/R | G60: N/N | H60: USD | I60: 4720 | J60: 5550 | K60: 5550 | L60: 7025 | Z60: 1,2,4 | AA60: E
... A71: FAK PSW | C71: NCPRC BP LAX | D71: LAX-LGB | E71: NORFOLK, VA | F71: CY/R | G71: N/N | H71: USD | I71: 5740 | J71: 6750 | K71: 6750 | L71: 8545 | Z71: 1,2,4 | AA71: E
A72: FAK PSW | C72: SPRC BP LAX | D72: LAX-LGB | F72: CY/CY | G72: N/N | H72: USD | I72: 1785 | J72: 2100 | K72: 2100 | L72: 2660 | Z72: 1,2,4 | AA72: E
A73: FAK PSW | C73: SPRC BP OAK | D73: OAKLAND, CA | F73: CY/CY | G73: N/N | H73: USD | I73: 1785 | J73: 2100 | K73: 2100 | L73: 2660 | Z73: 1,2,4 | AA73: E
A74: FAK PSW | C74: SPRC BP LAX | D74: LAX-LGB | E74: CHICAGO, IL | F74: CY/R | G74: N/N | H74: USD | I74: 3870 | J74: 4550 | K74: 4550 | L74: 5760 | Z74: 1,2,4 | AA74: E
A75: FAK PSW | C75: SPRC BP LAX | D75: LAX-LGB | E75: CINCINNATI, OH | F75: CY/R | G75: N/N | H75: USD | I75: 4380 | J75: 5150 | K75: 5150 | L75: 6520 | Z75: 1,2,4 | AA75: E
A76: FAK PSW | C76: SPRC BP LAX | D76: LAX-LGB | E76: CLEVELAND, OH | F76: CY/R | G76: N/N | H76: USD | I76: 4380 | J76: 5150 | K76: 5150 | L76: 6520 | Z76: 1,2,4 | AA76: E
A77: FAK PSW | C77: SPRC BP LAX | D77: LAX-LGB | E77: COLUMBUS, OH | F77: CY/R | G77: N/N | H77: USD | I77: 4380 | J77: 5150 | K77: 5150 | L77: 6520 | Z77: 1,2,4 | AA77: E
A78: FAK PSW | C78: SPRC BP LAX | D78: LAX-LGB | E78: DALLAS, TX | F78: CY/R | G78: N/N | H78: USD | I78: 3870 | J78: 4550 | K78: 4550 | L78: 5760 | Z78: 1,2,4 | AA78: E
A79: FAK PSW | C79: SPRC BP LAX | D79: LAX-LGB | E79: DENVER, CO | F79: CY/R | G79: N/N | H79: USD | I79: 4550 | J79: 5350 | K79: 5350 | L79: 6775 | Z79: 1,2,4 | AA79: E
A80: FAK PSW | C80: SPRC BP LAX | D80: LAX-LGB | E80: DETROIT, MI | F80: CY/R | G80: N/N | H80: USD | I80: 4720 | J80: 5550 | K80: 5550 | L80: 7025 | Z80: 1,2,4 | AA80: E
A81: FAK PSW | C81: SPRC BP LAX | D81: LAX-LGB | E81: EL PASO, TX | F81: CY/R | G81: N/N | H81: USD | I81: 4125 | J81: 4850 | K81: 4850 | L81: 6140 | Z81: 1,2,4 | AA81: E
A82: FAK PSW | C82: SPRC BP LAX | D82: LAX-LGB | E82: HOUSTON, TX | F82: CY/R | G82: N/N | H82: USD | I82: 4210 | J82: 4950 | K82: 4950 | L82: 6265 | Z82: 1,2,4 | AA82: E
A83: FAK PSW | C83: SPRC BP LAX | D83: LAX-LGB | E83: INDIANAPOLIS, IN | F83: CY/RM | G83: N/Y | H83: USD | I83: 6420 | J83: 7550 | K83: 7550 | L83: 9560 | Z83: 1,2,4 | AA83: E
A84: FAK PSW | C84: SPRC BP LAX | D84: LAX-LGB | E84: KANSAS CITY, KS | F84: CY/R | G84: N/N | H84: USD | I84: 3870 | J84: 4550 | K84: 4550 | L84: 5760 | Z84: 1,2,4 | AA84: E
A85: FAK PSW | C85: SPRC BP LAX | D85: LAX-LGB | E85: LOUISVILLE, KY | F85: CY/R | G85: N/N | H85: USD | I85: 4720 | J85: 5550 | K85: 5550 | L85: 7025 | Z85: 1,2,4 | AA85: E
... A96: FAK PSW | C96: SPRC BP LAX | D96: LAX-LGB | E96: NORFOLK, VA | F96: CY/R | G96: N/N | H96: USD | I96: 5740 | J96: 6750 | K96: 6750 | L96: 8545 | Z96: 1,2,4 | AA96: E
A97: FAK PSW | C97: BP TW | D97: LAX-LGB | F97: CY/CY | G97: N/N | H97: USD | I97: 1575 | J97: 2100 | K97: 2100 | L97: 2660 | Z97: 1,2,4 | AA97: E
A98: FAK PSW | C98: BP TW | D98: OAKLAND, CA | F98: CY/CY | G98: N/N | H98: USD | I98: 1575 | J98: 2100 | K98: 2100 | L98: 2660 | Z98: 1,2,4 | AA98: E
A99: FAK PSW | C99: BP TW | D99: LAX-LGB | E99: CHICAGO, IL | F99: CY/R | G99: N/N | H99: USD | I99: 3640 | J99: 4550 | K99: 4550 | L99: 5760 | Z99: 1,2,4 | AA99: E
A100: FAK PSW | C100: BP TW | D100: LAX-LGB | E100: CINCINNATI, OH | F100: CY/R | G100: N/N | H100: USD | I100: 4120 | J100: 5150 | K100: 5150 | L100: 6520 | Z100: 1,2,4 | AA100: E
A101: FAK PSW | C101: BP TW | D101: LAX-LGB | E101: CLEVELAND, OH | F101: CY/R | G101: N/N | H101: USD | I101: 4120 | J101: 5150 | K101: 5150 | L101: 6520 | Z101: 1,2,4 | AA101: E
A102: FAK PSW | C102: BP TW | D102: LAX-LGB | E102: COLUMBUS, OH | F102: CY/R | G102: N/N | H102: USD | I102: 4120 | J102: 5150 | K102: 5150 | L102: 6520 | Z102: 1,2,4 | AA102: E
A103: FAK PSW | C103: BP TW | D103: LAX-LGB | E103: DALLAS, TX | F103: CY/R | G103: N/N | H103: USD | I103: 3640 | J103: 4550 | K103: 4550 | L103: 5760 | Z103: 1,2,4 | AA103: E
A104: FAK PSW | C104: BP TW | D104: LAX-LGB | E104: DENVER, CO | F104: CY/R | G104: N/N | H104: USD | I104: 4280 | J104: 5350 | K104: 5350 | L104: 6775 | Z104: 1,2,4 | AA104: E
A105: FAK PSW | C105: BP TW | D105: LAX-LGB | E105: DETROIT, MI | F105: CY/R | G105: N/N | H105: USD | I105: 4440 | J105: 5550 | K105: 5550 | L105: 7025 | Z105: 1,2,4 | AA105: E
A106: FAK PSW | C106: BP TW | D106: LAX-LGB | E106: EL PASO, TX | F106: CY/R | G106: N/N | H106: USD | I106: 3880 | J106: 4850 | K106: 4850 | L106: 6140 | Z106: 1,2,4 | AA106: E
A107: FAK PSW | C107: BP TW | D107: LAX-LGB | E107: HOUSTON, TX | F107: CY/R | G107: N/N | H107: USD | I107: 3960 | J107: 4950 | K107: 4950 | L107: 6265 | Z107: 1,2,4 | AA107: E
A108: FAK PSW | C108: BP TW | D108: LAX-LGB | E108: INDIANAPOLIS, IN | F108: CY/RM | G108: N/Y | H108: USD | I108: 6040 | J108: 7550 | K108: 7550 | L108: 9560 | Z108: 1,2,4 | AA108: E
A109: FAK PSW | C109: BP TW | D109: LAX-LGB | E109: KANSAS CITY, KS | F109: CY/R | G109: N/N | H109: USD | I109: 3640 | J109: 4550 | K109: 4550 | L109: 5760 | Z109: 1,2,4 | AA109: E
A110: FAK PSW | C110: BP TW | D110: OAKLAND, CA | E110: KANSAS CITY, KS | F110: CY/R | G110: N/N | H110: USD | I110: 3640 | J110: 4550 | K110: 4550 | L110: 5760 | Z110: 1,2,4 | AA110: E
... A122: FAK PSW | C122: BP TW | D122: LAX-LGB | E122: NORFOLK, VA | F122: CY/R | G122: N/N | H122: USD | I122: 5400 | J122: 6750 | K122: 6750 | L122: 8545 | Z122: 1,2,4 | AA122: E
A123: FAK PSW | C123: BUSAN | D123: LAX-LGB | F123: CY/CY | G123: N/N | H123: USD | I123: 1680 | J123: 2100 | K123: 2100 | L123: 2660 | Z123: 1,2,4 | AA123: E
A124: FAK PSW | C124: BUSAN | D124: OAKLAND, CA | F124: CY/CY | G124: N/N | H124: USD | I124: 1680 | J124: 2100 | K124: 2100 | L124: 2660 | Z124: 1,2,4 | AA124: E
A125: FAK PSW | C125: BUSAN | D125: LAX-LGB | E125: CHICAGO, IL | F125: CY/R | G125: N/N | H125: USD | I125: 3870 | J125: 4550 | K125: 4550 | L125: 5760 | Z125: 1,2,4 | AA125: E
A126: FAK PSW | C126: BUSAN | D126: LAX-LGB | E126: CINCINNATI, OH | F126: CY/R | G126: N/N | H126: USD | I126: 4380 | J126: 5150 | K126: 5150 | L126: 6520 | Z126: 1,2,4 | AA126: E
A127: FAK PSW | C127: BUSAN | D127: LAX-LGB | E127: CLEVELAND, OH | F127: CY/R | G127: N/N | H127: USD | I127: 4380 | J127: 5150 | K127: 5150 | L127: 6520 | Z127: 1,2,4 | AA127: E
A128: FAK PSW | C128: BUSAN | D128: LAX-LGB | E128: COLUMBUS, OH | F128: CY/R | G128: N/N | H128: USD | I128: 4380 | J128: 5150 | K128: 5150 | L128: 6520 | Z128: 1,2,4 | AA128: E
A129: FAK PSW | C129: BUSAN | D129: LAX-LGB | E129: DALLAS, TX | F129: CY/R | G129: N/N | H129: USD | I129: 3870 | J129: 4550 | K129: 4550 | L129: 5760 | Z129: 1,2,4 | AA129: E
A130: FAK PSW | C130: BUSAN | D130: LAX-LGB | E130: DENVER, CO | F130: CY/R | G130: N/N | H130: USD | I130: 4550 | J130: 5350 | K130: 5350 | L130: 6775 | Z130: 1,2,4 | AA130: E
A131: FAK PSW | C131: BUSAN | D131: LAX-LGB | E131: DETROIT, MI | F131: CY/R | G131: N/N | H131: USD | I131: 4720 | J131: 5550 | K131: 5550 | L131: 7025 | Z131: 1,2,4 | AA131: E
A132: FAK PSW | C132: BUSAN | D132: LAX-LGB | E132: EL PASO, TX | F132: CY/R | G132: N/N | H132: USD | I132: 4125 | J132: 4850 | K132: 4850 | L132: 6140 | Z132: 1,2,4 | AA132: E
A133: FAK PSW | C133: BUSAN | D133: LAX-LGB | E133: HOUSTON, TX | F133: CY/R | G133: N/N | H133: USD | I133: 4210 | J133: 4950 | K133: 4950 | L133: 6265 | Z133: 1,2,4 | AA133: E
A134: FAK PSW | C134: BUSAN | D134: LAX-LGB | E134: INDIANAPOLIS, IN | F134: CY/RM | G134: N/Y | H134: USD | I134: 6420 | J134: 7550 | K134: 7550 | L134: 9560 | Z134: 1,2,4 | AA134: E
A135: FAK PSW | C135: BUSAN | D135: LAX-LGB | E135: KANSAS CITY, KS | F135: CY/R | G135: N/N | H135: USD | I135: 3870 | J135: 4550 | K135: 4550 | L135: 5760 | Z135: 1,2,4 | AA135: E
A136: FAK PSW | C136: BUSAN | D136: LAX-LGB | E136: LOUISVILLE, KY | F136: CY/R | G136: N/N | H136: USD | I136: 4720 | J136: 5550 | K136: 5550 | L136: 7025 | Z136: 1,2,4 | AA136: E
... A147: FAK PSW | C147: BUSAN | D147: LAX-LGB | E147: NORFOLK, VA | F147: CY/R | G147: N/N | H147: USD | I147: 5740 | J147: 6750 | K147: 6750 | L147: 8545 | Z147: 1,2,4 | AA147: E
A148: FAK PSW | C148: SE ASIA BP PSW | D148: LAX-LGB | F148: CY/CY | G148: N/N | H148: USD | I148: 1785 | J148: 2100 | K148: 2100 | L148: 2660 | Z148: 1,2,4 | AA148: E
A149: FAK PSW | C149: SE ASIA BP PSW | D149: OAKLAND, CA | F149: CY/CY | G149: N/N | H149: USD | I149: 1785 | J149: 2100 | K149: 2100 | L149: 2660 | Z149: 1,2,4 | AA149: E
A150: FAK PSW | C150: SE ASIA BP PSW | D150: LAX-LGB | E150: CHICAGO, IL | F150: CY/R | G150: N/N | H150: USD | I150: 3870 | J150: 4550 | K150: 4550 | L150: 5760 | Z150: 1,2,4 | AA150: E
...

Sheet APPENDIX B-2  (FE - USEC&GC)
A1: Service Contract: | C1: =Cover!B1 -> 25-3117
A2: TERM 6
A3: Amendment Number: | C3: =Cover!B2 -> 58
A4: Merchant Name: | C4: =Cover!B7 -> LOGISTIQUE PRIME FREIGHT INC
A5: Appendix: | C5: B-2
A6: Trade Service: | C6: INBOUND FAR EAST (ASIA-USEC & USGC)
A7: TARIFF applicability | C7: CMDU#043 B2
A9: 41 | B9: INB
A11: COMMODITY INDEX
A12: - Unless otherwise indicated, excludes temperature controlled cargo, hazardous cargo, cargo requiring special handling and/or equipment, overweight containers.
A13: FAK/Bullets | B13: Description | J13: Named Account | L13: Partner Code | N13: ALL
A14: FAK BAL | B14: FAK | N14: =IF($A14>0,$A14,"") -> FAK BAL
A15: FAK EC | B15: FAK | N15: =IF($A15>0,$A15,"") -> FAK EC
A16: FAK GCFL | B16: FAK | N16: =IF($A16>0,$A16,"") -> FAK GCFL
A17: FAK MIA | B17: FAK | N17: =IF($A17>0,$A17,"") -> FAK MIA
A18: FAK BOS | B18: FAK
N19: =IF($A19>0,$A19,"")
N20: =IF($A20>0,$A20,"")
N21: =IF($A21>0,$A21,"")
N22: =IF($A22>0,$A22,"")
A23: Port Group Codes
A24: Port Group Codes | B24: Description
A25: BP BAL | B25: XIAMEN,HONG KONG,YANTIAN
A26: SE ASIA BP GCFL | B26: VUNG TAU,SINGAPORE
A27: GULF | B27: HOUSTON,MOBILE,NEW ORLEANS
A28: BP JAPAN | B28: NAGOYA, SHIMIZU, TOKYO, KOBE, YOKOHAMA, OSAKA, HIROSHIMA, MOJI, HAKATA/FUKUOKA
A29: NCPRC BP EC | B29: SHANGHAI,NINGBO,QINGDAO
A30: SE ASIA BP EC | B30: VUNG TAU,PORT KLANG,SINGAPORE,HAIPHONG
A31: BP MIA | B31: PORT KLANG,HAIPHONG,YANTIAN,NINGBO,SHANGHAI,XIAMEN,SHEKOU
A32: BP GCFL | B32: NINGBO,SHANGHAI,XIAMEN,YANTIAN,SHEKOU
A33: SPRC BP EC | B33: YANTIAN,SHEKOU,XIAMEN,HONG KONG,YANGPU
A37: RATES CONDITIONS
A38: Rates in USD unless otherwise specified. Surcharges listed per line item are exceptions to Note 2 applicability.
A39: For Place of Receipt indicate origin of cargo
A40: For Place of Intermodal Delivery indicate point and state. Mode: PORT=CY, RAIL=R (RAMP), MOTOR=M , RAIL/MOTOR=RM , BARGE=B, RAIL/BARGE=RB (RAMP), MOTOR/BARGE=BM
A41: FAK/ BULLETS | B41: Place of Receipt | C41: POL | D41: POD | E41: Place of Delivery | F41: MODE | G41: SDD (Origin; Dest) | H41: Curr | I41: D20 | J41: D40 | K41: H40 | L41: H45 | X41: Effective date | Y41: Expiration Date | Z41: Note | AA41: IPI Construction
A43: FAK BAL | C43: BP BAL | D43: BALTIMORE, MD | F43: CY/CY | G43: N/N | H43: USD | I43: 2080 | J43: 2600 | K43: 2600 | L43: 3290 | Z43: 1,2,4 | AA43: E
A44: FAK BAL | C44: KAOHSIUNG | D44: BALTIMORE, MD | F44: CY/CY | G44: N/N | H44: USD | I44: 2080 | J44: 2600 | K44: 2600 | L44: 3290 | Z44: 1,2,4 | AA44: E
A45: FAK BAL | C45: LAEM CHABANG | D45: BALTIMORE, MD | F45: CY/CY | G45: N/N | H45: USD | I45: 2160 | J45: 2700 | K45: 2700 | L45: 3420 | Z45: 1,2,4 | AA45: E
A46: FAK BAL | C46: VUNG TAU | D46: BALTIMORE, MD | F46: CY/CY | G46: N/N | H46: USD | I46: 2160 | J46: 2700 | K46: 2700 | L46: 3420 | Z46: 1,2,4 | AA46: E
A47: FAK EC | C47: NCPRC BP EC | D47: NEW YORK, NY | F47: CY/CY | G47: N/N | H47: USD | I47: 2120 | J47: 2650 | K47: 2650 | L47: 3355 | Z47: 1,2,4 | AA47: B
A48: FAK EC | C48: NCPRC BP EC | D48: NORFOLK, VA | F48: CY/CY | G48: N/N | H48: USD | I48: 2120 | J48: 2650 | K48: 2650 | L48: 3355 | Z48: 1,2,4 | AA48: E
A49: FAK EC | C49: NCPRC BP EC | D49: SAVANNAH, GA | F49: CY/CY | G49: N/N | H49: USD | I49: 2120 | J49: 2650 | K49: 2650 | L49: 3355 | Z49: 1,2,4 | AA49: B
A50: FAK EC | C50: NCPRC BP EC | D50: CHARLESTON, SC | F50: CY/CY | G50: N/N | H50: USD | I50: 2120 | J50: 2650 | K50: 2650 | L50: 3355 | Z50: 1,2,4 | AA50: E
A51: FAK EC | C51: NCPRC BP EC | D51: SAVANNAH, GA | E51: ATLANTA, GA | F51: CY/R | G51: N/N | H51: USD | I51: 2720 | J51: 3400 | K51: 3400 | L51: 4305 | Z51: 1,2,4 | AA51: E
A52: FAK EC | C52: NCPRC BP EC | D52: NEW YORK, NY | E52: BUFFALO, NY | F52: CY/R | G52: N/N | H52: USD | I52: 3160 | J52: 3950 | K52: 3950 | L52: 5000 | Z52: 1,2,4 | AA52: E
A53: FAK EC | C53: NCPRC BP EC | D53: SAVANNAH, GA | E53: CHARLOTTE, NC | F53: CY/R | G53: N/N | H53: USD | I53: 2720 | J53: 3400 | K53: 3400 | L53: 4305 | Z53: 1,2,4 | AA53: E
A54: FAK EC | C54: NCPRC BP EC | D54: SAVANNAH, GA | E54: CHATSWORTH, GA | F54: CY/R | G54: N/N | H54: USD | I54: 2920 | J54: 3650 | K54: 3650 | L54: 4620 | Z54: 1,2,4 | AA54: E
A55: FAK EC | C55: NCPRC BP EC | D55: NEW YORK, NY | E55: CHICAGO, IL | F55: CY/R | G55: N/N | H55: USD | I55: 3160 | J55: 3950 | K55: 3950 | L55: 5000 | Z55: 1,2,4 | AA55: E
A56: FAK EC | C56: NCPRC BP EC | D56: NORFOLK, VA | E56: CHICAGO, IL | F56: CY/R | G56: N/N | H56: USD | I56: 3160 | J56: 3950 | K56: 3950 | L56: 5000 | Z56: 1,2,4 | AA56: E
A57: FAK EC | C57: NCPRC BP EC | D57: NEW YORK, NY | E57: CINCINNATI, OH | F57: CY/R | G57: N/N | H57: USD | I57: 3160 | J57: 3950 | K57: 3950 | L57: 5000 | Z57: 1,2,4 | AA57: E
A58: FAK EC | C58: NCPRC BP EC | D58: NORFOLK, VA | E58: CINCINNATI, OH | F58: CY/R | G58: N/N | H58: USD | I58: 3160 | J58: 3950 | K58: 3950 | L58: 5000 | Z58: 1,2,4 | AA58: E
A59: FAK EC | C59: NCPRC BP EC | D59: NEW YORK, NY | E59: CLEVELAND, OH | F59: CY/R | G59: N/N | H59: USD | I59: 3040 | J59: 3800 | K59: 3800 | L59: 4810 | Z59: 1,2,4 | AA59: E
A60: FAK EC | C60: NCPRC BP EC | D60: NORFOLK, VA | E60: CLEVELAND, OH | F60: CY/R | G60: N/N | H60: USD | I60: 3040 | J60: 3800 | K60: 3800 | L60: 4810 | Z60: 1,2,4 | AA60: E
A61: FAK EC | C61: NCPRC BP EC | D61: NEW YORK, NY | E61: COLUMBUS, OH | F61: CY/R | G61: N/N | H61: USD | I61: 3200 | J61: 4000 | K61: 4000 | L61: 5065 | Z61: 1,2,4 | AA61: E
A62: FAK EC | C62: NCPRC BP EC | D62: NORFOLK, VA | E62: COLUMBUS, OH | F62: CY/R | G62: N/N | H62: USD | I62: 3200 | J62: 4000 | K62: 4000 | L62: 5065 | Z62: 1,2,4 | AA62: E
... A72: FAK EC | C72: NCPRC BP EC | D72: NORFOLK, VA | E72: ST LOUIS, MO | F72: CY/R | G72: N/N | H72: USD | I72: 3080 | J72: 3850 | K72: 3850 | L72: 4875 | Z72: 1,2,4 | AA72: E
A73: FAK EC | C73: SPRC BP EC | D73: NEW YORK, NY | F73: CY/CY | G73: N/N | H73: USD | I73: 2120 | J73: 2650 | K73: 2650 | L73: 3355 | Z73: 1,2,4 | AA73: B
A74: FAK EC | C74: SPRC BP EC | D74: NORFOLK, VA | F74: CY/CY | G74: N/N | H74: USD | I74: 2120 | J74: 2650 | K74: 2650 | L74: 3355 | Z74: 1,2,4 | AA74: E
A75: FAK EC | C75: SPRC BP EC | D75: SAVANNAH, GA | F75: CY/CY | G75: N/N | H75: USD | I75: 2120 | J75: 2650 | K75: 2650 | L75: 3355 | Z75: 1,2,4 | AA75: B
A76: FAK EC | C76: SPRC BP EC | D76: CHARLESTON, SC | F76: CY/CY | G76: N/N | H76: USD | I76: 2120 | J76: 2650 | K76: 2650 | L76: 3355 | Z76: 1,2,4 | AA76: E
A77: FAK EC | C77: SPRC BP EC | D77: SAVANNAH, GA | E77: ATLANTA, GA | F77: CY/R | G77: N/N | H77: USD | I77: 2720 | J77: 3400 | K77: 3400 | L77: 4305 | Z77: 1,2,4 | AA77: E
A78: FAK EC | C78: SPRC BP EC | D78: NEW YORK, NY | E78: BUFFALO, NY | F78: CY/R | G78: N/N | H78: USD | I78: 3160 | J78: 3950 | K78: 3950 | L78: 5000 | Z78: 1,2,4 | AA78: E
A79: FAK EC | C79: SPRC BP EC | D79: SAVANNAH, GA | E79: CHARLOTTE, NC | F79: CY/R | G79: N/N | H79: USD | I79: 2720 | J79: 3400 | K79: 3400 | L79: 4305 | Z79: 1,2,4 | AA79: E
A80: FAK EC | C80: SPRC BP EC | D80: SAVANNAH, GA | E80: CHATSWORTH, GA | F80: CY/R | G80: N/N | H80: USD | I80: 2920 | J80: 3650 | K80: 3650 | L80: 4620 | Z80: 1,2,4 | AA80: E
A81: FAK EC | C81: SPRC BP EC | D81: NEW YORK, NY | E81: CHICAGO, IL | F81: CY/R | G81: N/N | H81: USD | I81: 3160 | J81: 3950 | K81: 3950 | L81: 5000 | Z81: 1,2,4 | AA81: E
A82: FAK EC | C82: SPRC BP EC | D82: NORFOLK, VA | E82: CHICAGO, IL | F82: CY/R | G82: N/N | H82: USD | I82: 3160 | J82: 3950 | K82: 3950 | L82: 5000 | Z82: 1,2,4 | AA82: E
A83: FAK EC | C83: SPRC BP EC | D83: NEW YORK, NY | E83: CINCINNATI, OH | F83: CY/R | G83: N/N | H83: USD | I83: 3160 | J83: 3950 | K83: 3950 | L83: 5000 | Z83: 1,2,4 | AA83: E
A84: FAK EC | C84: SPRC BP EC | D84: NORFOLK, VA | E84: CINCINNATI, OH | F84: CY/R | G84: N/N | H84: USD | I84: 3160 | J84: 3950 | K84: 3950 | L84: 5000 | Z84: 1,2,4 | AA84: E
A85: FAK EC | C85: SPRC BP EC | D85: NEW YORK, NY | E85: CLEVELAND, OH | F85: CY/R | G85: N/N | H85: USD | I85: 3040 | J85: 3800 | K85: 3800 | L85: 4810 | Z85: 1,2,4 | AA85: E
A86: FAK EC | C86: SPRC BP EC | D86: NORFOLK, VA | E86: CLEVELAND, OH | F86: CY/R | G86: N/N | H86: USD | I86: 3040 | J86: 3800 | K86: 3800 | L86: 4810 | Z86: 1,2,4 | AA86: E
A87: FAK EC | C87: SPRC BP EC | D87: NEW YORK, NY | E87: COLUMBUS, OH | F87: CY/R | G87: N/N | H87: USD | I87: 3200 | J87: 4000 | K87: 4000 | L87: 5065 | Z87: 1,2,4 | AA87: E
A88: FAK EC | C88: SPRC BP EC | D88: NORFOLK, VA | E88: COLUMBUS, OH | F88: CY/R | G88: N/N | H88: USD | I88: 3200 | J88: 4000 | K88: 4000 | L88: 5065 | Z88: 1,2,4 | AA88: E
... A98: FAK EC | C98: SPRC BP EC | D98: NORFOLK, VA | E98: ST LOUIS, MO | F98: CY/R | G98: N/N | H98: USD | I98: 3080 | J98: 3850 | K98: 3850 | L98: 4875 | Z98: 1,2,4 | AA98: E
A99: FAK EC | C99: KAOHSIUNG | D99: NEW YORK, NY | F99: CY/CY | G99: N/N | H99: USD | I99: 2120 | J99: 2650 | K99: 2650 | L99: 3355 | Z99: 1,2,4 | AA99: B
A100: FAK EC | C100: KAOHSIUNG | D100: NORFOLK, VA | F100: CY/CY | G100: N/N | H100: USD | I100: 2120 | J100: 2650 | K100: 2650 | L100: 3355 | Z100: 1,2,4 | AA100: E
A101: FAK EC | C101: KAOHSIUNG | D101: SAVANNAH, GA | F101: CY/CY | G101: N/N | H101: USD | I101: 2120 | J101: 2650 | K101: 2650 | L101: 3355 | Z101: 1,2,4 | AA101: B
A102: FAK EC | C102: KAOHSIUNG | D102: CHARLESTON, SC | F102: CY/CY | G102: N/N | H102: USD | I102: 2120 | J102: 2650 | K102: 2650 | L102: 3355 | Z102: 1,2,4 | AA102: E
A103: FAK EC | C103: KAOHSIUNG | D103: SAVANNAH, GA | E103: ATLANTA, GA | F103: CY/R | G103: N/N | H103: USD | I103: 2720 | J103: 3400 | K103: 3400 | L103: 4305 | Z103: 1,2,4 | AA103: E
A104: FAK EC | C104: KAOHSIUNG | D104: NEW YORK, NY | E104: BUFFALO, NY | F104: CY/R | G104: N/N | H104: USD | I104: 3160 | J104: 3950 | K104: 3950 | L104: 5000 | Z104: 1,2,4 | AA104: E
A105: FAK EC | C105: KAOHSIUNG | D105: SAVANNAH, GA | E105: CHARLOTTE, NC | F105: CY/R | G105: N/N | H105: USD | I105: 2720 | J105: 3400 | K105: 3400 | L105: 4305 | Z105: 1,2,4 | AA105: E
A106: FAK EC | C106: KAOHSIUNG | D106: SAVANNAH, GA | E106: CHATSWORTH, GA | F106: CY/R | G106: N/N | H106: USD | I106: 2920 | J106: 3650 | K106: 3650 | L106: 4620 | Z106: 1,2,4 | AA106: E
A107: FAK EC | C107: KAOHSIUNG | D107: NEW YORK, NY | E107: CHICAGO, IL | F107: CY/R | G107: N/N | H107: USD | I107: 3160 | J107: 3950 | K107: 3950 | L107: 5000 | Z107: 1,2,4 | AA107: E
A108: FAK EC | C108: KAOHSIUNG | D108: NORFOLK, VA | E108: CHICAGO, IL | F108: CY/R | G108: N/N | H108: USD | I108: 3160 | J108: 3950 | K108: 3950 | L108: 5000 | Z108: 1,2,4 | AA108: E
A109: FAK EC | C109: KAOHSIUNG | D109: NEW YORK, NY | E109: CINCINNATI, OH | F109: CY/R | G109: N/N | H109: USD | I109: 3160 | J109: 3950 | K109: 3950 | L109: 5000 | Z109: 1,2,4 | AA109: E
A110: FAK EC | C110: KAOHSIUNG | D110: NORFOLK, VA | E110: CINCINNATI, OH | F110: CY/R | G110: N/N | H110: USD | I110: 3160 | J110: 3950 | K110: 3950 | L110: 5000 | Z110: 1,2,4 | AA110: E
A111: FAK EC | C111: KAOHSIUNG | D111: NEW YORK, NY | E111: CLEVELAND, OH | F111: CY/R | G111: N/N | H111: USD | I111: 3040 | J111: 3800 | K111: 3800 | L111: 4810 | Z111: 1,2,4 | AA111: E
A112: FAK EC | C112: KAOHSIUNG | D112: NORFOLK, VA | E112: CLEVELAND, OH | F112: CY/R | G112: N/N | H112: USD | I112: 3040 | J112: 3800 | K112: 3800 | L112: 4810 | Z112: 1,2,4 | AA112: E
A113: FAK EC | C113: KAOHSIUNG | D113: NEW YORK, NY | E113: COLUMBUS, OH | F113: CY/R | G113: N/N | H113: USD | I113: 3200 | J113: 4000 | K113: 4000 | L113: 5065 | Z113: 1,2,4 | AA113: E
A114: FAK EC | C114: KAOHSIUNG | D114: NORFOLK, VA | E114: COLUMBUS, OH | F114: CY/R | G114: N/N | H114: USD | I114: 3200 | J114: 4000 | K114: 4000 | L114: 5065 | Z114: 1,2,4 | AA114: E
... A124: FAK EC | C124: KAOHSIUNG | D124: NORFOLK, VA | E124: ST LOUIS, MO | F124: CY/R | G124: N/N | H124: USD | I124: 3080 | J124: 3850 | K124: 3850 | L124: 4875 | Z124: 1,2,4 | AA124: E
A125: FAK EC | C125: BUSAN | D125: NEW YORK, NY | F125: CY/CY | G125: N/N | H125: USD | I125: 2120 | J125: 2650 | K125: 2650 | L125: 3355 | Z125: 1,2,4 | AA125: B
A126: FAK EC | C126: BUSAN | D126: NORFOLK, VA | F126: CY/CY | G126: N/N | H126: USD | I126: 2120 | J126: 2650 | K126: 2650 | L126: 3355 | Z126: 1,2,4 | AA126: E
A127: FAK EC | C127: BUSAN | D127: SAVANNAH, GA | F127: CY/CY | G127: N/N | H127: USD | I127: 2120 | J127: 2650 | K127: 2650 | L127: 3355 | Z127: 1,2,4 | AA127: B
A128: FAK EC | C128: BUSAN | D128: CHARLESTON, SC | F128: CY/CY | G128: N/N | H128: USD | I128: 2120 | J128: 2650 | K128: 2650 | L128: 3355 | Z128: 1,2,4 | AA128: E
A129: FAK EC | C129: BUSAN | D129: SAVANNAH, GA | E129: ATLANTA, GA | F129: CY/R | G129: N/N | H129: USD | I129: 2720 | J129: 3400 | K129: 3400 | L129: 4305 | Z129: 1,2,4 | AA129: E
A130: FAK EC | C130: BUSAN | D130: NEW YORK, NY | E130: BUFFALO, NY | F130: CY/R | G130: N/N | H130: USD | I130: 3160 | J130: 3950 | K130: 3950 | L130: 5000 | Z130: 1,2,4 | AA130: E
A131: FAK EC | C131: BUSAN | D131: SAVANNAH, GA | E131: CHARLOTTE, NC | F131: CY/R | G131: N/N | H131: USD | I131: 2720 | J131: 3400 | K131: 3400 | L131: 4305 | Z131: 1,2,4 | AA131: E
A132: FAK EC | C132: BUSAN | D132: SAVANNAH, GA | E132: CHATSWORTH, GA | F132: CY/R | G132: N/N | H132: USD | I132: 2920 | J132: 3650 | K132: 3650 | L132: 4620 | Z132: 1,2,4 | AA132: E
A133: FAK EC | C133: BUSAN | D133: NEW YORK, NY | E133: CHICAGO, IL | F133: CY/R | G133: N/N | H133: USD | I133: 3160 | J133: 3950 | K133: 3950 | L133: 5000 | Z133: 1,2,4 | AA133: E
...

Sheet APPENDIX F-1 ISC-US
A1: Service Contract: | C1: =Cover!B1 -> 25-3117
A2: TERM 6
A3: Amendment Number: | C3: =Cover!B2 -> 58
A4: Merchant Name: | C4: =Cover!B7 -> LOGISTIQUE PRIME FREIGHT INC
A5: Appendix: | C5: F-1
A6: Trade Service: | C6: INBOUND (INDIAN SUB. CONTINENT-USA EC) (INDAMEX)
A7: TARIFF applicability | C7: CMDU#029 F1
A9: 43 | B9: INB
A11: COMMODITY INDEX
A12: - Unless otherwise indicated, excludes temperature controlled cargo, hazardous cargo, cargo requiring special handling and/or equipment, overweight containers.
A13: FAK/Bullets | B13: Description | J13: Named Account | L13: Partner Code | N13: ALL
A14: FAK BD | B14: FAK | N14: =IF($A14>0,$A14,"") -> FAK BD
N15: =IF($A15>0,$A15,"")
N16: =IF($A16>0,$A16,"")
N17: =IF($A17>0,$A17,"")
N18: =IF($A18>0,$A18,"")
A19: Port Group Codes
A20: Port Group Codes | B20: Description
A26: RATES CONDITIONS
A27: Rates in USD unless otherwise specified. Surcharges listed per line item are exceptions to Note 2 applicability.
A28: For Place of Receipt indicate origin of cargo
A29: For Place of Intermodal Delivery indicate point and state. Mode: PORT=CY, RAIL=R (RAMP), MOTOR=M , RAIL/MOTOR=RM , BARGE=B, RAIL/BARGE=RB (RAMP), MOTOR/BARGE=BM
A30: FAK/ BULLETS | B30: Place of Receipt | C30: POL | D30: POD | E30: Place of Delivery | F30: MODE | G30: SDD (Origin; Dest) | H30: Curr | I30: D20 | J30: D40 | K30: H40 | L30: H45 | M30: PSS | N30: PSS2 | O30: PSS3 | P30: BAF | X30: Effective date | Y30: Expiration Date | Z30: Note | AA30: IPI Construction
M31: Appl/ Not Appl | N31: Appl/ Not Appl | O31: Appl/ Not Appl | P31: Appl/ Not Appl
A32: FAK BD | C32: CHITTAGONG | D32: CHARLESTON, SC | F32: CY/CY | G32: N/N | H32: USD | I32: 3060 | J32: 3400 | K32: 3400 | L32: 4305 | M32: Not Applicable | N32: Not Applicable | O32: Not Applicable | P32: Not Applicable | Z32: 1,2,3,4 | AA32: B
A33: FAK BD | C33: CHITTAGONG | D33: NORFOLK, VA | F33: CY/CY | G33: N/N | H33: USD | I33: 3060 | J33: 3400 | K33: 3400 | L33: 4305 | M33: Not Applicable | N33: Not Applicable | O33: Not Applicable | P33: Not Applicable | Z33: 1,2,3,4 | AA33: B
A34: FAK BD | C34: CHITTAGONG | D34: SAVANNAH, GA | F34: CY/CY | G34: N/N | H34: USD | I34: 3060 | J34: 3400 | K34: 3400 | L34: 4305 | M34: Not Applicable | N34: Not Applicable | O34: Not Applicable | P34: Not Applicable | Z34: 1,2,3,4 | AA34: B
A35: FAK BD | C35: CHITTAGONG | D35: NEW YORK, NY | F35: CY/CY | G35: N/N | H35: USD | I35: 3060 | J35: 3400 | K35: 3400 | L35: 4305 | M35: Not Applicable | N35: Not Applicable | O35: Not Applicable | P35: Not Applicable | Z35: 1,2,3,4 | AA35: B
A36: FAK BD | C36: CHITTAGONG | D36: BALTIMORE, MD | F36: CY/CY | G36: N/N | H36: USD | I36: 4905 | J36: 5450 | K36: 5450 | L36: 6900 | M36: Not Applicable | N36: Not Applicable | O36: Not Applicable | P36: Not Applicable | Z36: 1,2,3,4 | AA36: B
A37: FAK BD | C37: CHITTAGONG | D37: SAVANNAH, GA | E37: ATLANTA, GA | F37: CY/R | G37: N/N | H37: USD | I37: 4050 | J37: 4500 | K37: 4500 | L37: 5695 | M37: Not Applicable | N37: Not Applicable | O37: Not Applicable | P37: Not Applicable | Z37: 1,2,3,4 | AA37: B
A38: FAK BD | C38: CHITTAGONG | D38: SAVANNAH, GA | E38: CHARLOTTE, NC | F38: CY/R | G38: N/N | H38: USD | I38: 4500 | J38: 5000 | K38: 5000 | L38: 6330 | M38: Not Applicable | N38: Not Applicable | O38: Not Applicable | P38: Not Applicable | Z38: 1,2,3,4 | AA38: B
A39: FAK BD | C39: CHITTAGONG | D39: SAVANNAH, GA | E39: CHATSWORTH, GA | F39: CY/R | G39: N/N | H39: USD | I39: 4140 | J39: 4600 | K39: 4600 | L39: 5825 | M39: Not Applicable | N39: Not Applicable | O39: Not Applicable | P39: Not Applicable | Z39: 1,2,3,4 | AA39: B
A40: FAK BD | C40: CHITTAGONG | D40: CHARLESTON, SC | E40: GREER, SC | F40: CY/R | G40: N/N | H40: USD | I40: 4590 | J40: 5100 | K40: 5100 | L40: 6455 | M40: Not Applicable | N40: Not Applicable | O40: Not Applicable | P40: Not Applicable | Z40: 1,2,3,4 | AA40: B
A41: FAK BD | C41: CHITTAGONG | D41: CHARLESTON, SC | E41: DILLON, SC | F41: CY/R | G41: N/N | H41: USD | I41: 4590 | J41: 5100 | K41: 5100 | L41: 6455 | M41: Not Applicable | N41: Not Applicable | O41: Not Applicable | P41: Not Applicable | Z41: 1,2,3,4 | AA41: B
A42: FAK BD | C42: CHITTAGONG | D42: NEW YORK, NY | E42: CHICAGO, IL | F42: CY/R | G42: N/N | H42: USD | I42: 4860 | J42: 5400 | K42: 5400 | L42: 6835 | M42: Not Applicable | N42: Not Applicable | O42: Not Applicable | P42: Not Applicable | Z42: 1,2,3,4 | AA42: B
A43: FAK BD | C43: CHITTAGONG | D43: NORFOLK, VA | E43: CHICAGO, IL | F43: CY/R | G43: N/N | H43: USD | I43: 4860 | J43: 5400 | K43: 5400 | L43: 6835 | M43: Not Applicable | N43: Not Applicable | O43: Not Applicable | P43: Not Applicable | Z43: 1,2,3,4 | AA43: B
A44: FAK BD | C44: CHITTAGONG | D44: NEW YORK, NY | E44: CINCINNATI, OH | F44: CY/R | G44: N/N | H44: USD | I44: 4680 | J44: 5200 | K44: 5200 | L44: 6585 | M44: Not Applicable | N44: Not Applicable | O44: Not Applicable | P44: Not Applicable | Z44: 1,2,3,4 | AA44: B
A45: FAK BD | C45: CHITTAGONG | D45: NORFOLK, VA | E45: CINCINNATI, OH | F45: CY/R | G45: N/N | H45: USD | I45: 4680 | J45: 5200 | K45: 5200 | L45: 6585 | M45: Not Applicable | N45: Not Applicable | O45: Not Applicable | P45: Not Applicable | Z45: 1,2,3,4 | AA45: B
A46: FAK BD | C46: CHITTAGONG | D46: NEW YORK, NY | E46: CLEVELAND, OH | F46: CY/R | G46: N/N | H46: USD | I46: 4680 | J46: 5200 | K46: 5200 | L46: 6585 | M46: Not Applicable | N46: Not Applicable | O46: Not Applicable | P46: Not Applicable | Z46: 1,2,3,4 | AA46: B
A47: FAK BD | C47: CHITTAGONG | D47: NORFOLK, VA | E47: CLEVELAND, OH | F47: CY/R | G47: N/N | H47: USD | I47: 4680 | J47: 5200 | K47: 5200 | L47: 6585 | M47: Not Applicable | N47: Not Applicable | O47: Not Applicable | P47: Not Applicable | Z47: 1,2,3,4 | AA47: B
A48: FAK BD | C48: CHITTAGONG | D48: NEW YORK, NY | E48: COLUMBUS, OH | F48: CY/R | G48: N/N | H48: USD | I48: 4680 | J48: 5200 | K48: 5200 | L48: 6585 | M48: Not Applicable | N48: Not Applicable | O48: Not Applicable | P48: Not Applicable | Z48: 1,2,3,4 | AA48: B
... A60: FAK BD | C60: CHITTAGONG | D60: HALIFAX, NS | E60: CHICAGO, IL | F60: CY/R | G60: N/N | H60: USD | I60: 4680 | J60: 5200 | K60: 5200 | L60: 6585 | M60: Not Applicable | N60: Not Applicable | O60: Not Applicable | P60: Not Applicable | Z60: 1,2,3,4 | AA60: B
A61: FAK BD | C61: CHITTAGONG | D61: MIAMI, FL | F61: CY/CY | G61: N/N | H61: USD | I61: 4635 | J61: 5150 | K61: 5150 | L61: 6520 | M61: Not Applicable | N61: Not Applicable | O61: Not Applicable | P61: Not Applicable | Z61: 1,2,3,4 | AA61: B
A62: FAK BD | C62: CHITTAGONG | D62: HOUSTON, TX | F62: CY/CY | G62: N/N | H62: USD | I62: 4635 | J62: 5150 | K62: 5150 | L62: 6520 | M62: Not Applicable | N62: Not Applicable | O62: Not Applicable | P62: Not Applicable | Z62: 1,2,3,4 | AA62: B
A63: FAK BD | C63: CHITTAGONG | D63: MOBILE, AL | F63: CY/CY | G63: N/N | H63: USD | I63: 4635 | J63: 5150 | K63: 5150 | L63: 6520 | M63: Not Applicable | N63: Not Applicable | O63: Not Applicable | P63: Not Applicable | Z63: 1,2,3,4 | AA63: B
A64: FAK BD | C64: CHITTAGONG | D64: NEW ORLEANS, LA | F64: CY/CY | G64: N/N | H64: USD | I64: 4635 | J64: 5150 | K64: 5150 | L64: 6520 | M64: Not Applicable | N64: Not Applicable | O64: Not Applicable | P64: Not Applicable | Z64: 1,2,3,4 | AA64: B
A65: FAK BD | C65: CHITTAGONG | D65: TAMPA, FL | F65: CY/CY | G65: N/N | H65: USD | I65: 4635 | J65: 5150 | K65: 5150 | L65: 6520 | M65: Not Applicable | N65: Not Applicable | O65: Not Applicable | P65: Not Applicable | Z65: 1,2,3,4 | AA65: B
A70: REEFER
A71: FAK/ BULLETS | B71: Place of Receipt | C71: POL | D71: POD | E71: Place of Delivery | F71: MODE | G71: SDD (Origin; Dest) | H71: Curr | I71: RF20 | J71: RF40 | K71: RH40 | L71: Type | M71: Shipper own | N71: Hazardous | X71: Effective date | Y71: Expiration Date | Z71: Note | AA71: IPI Construction
L72: Operated Yes / No | M72: SOC COC | N72: Yes / No
A79: SPECIAL EQUIPMENT, HAZARDOUS, SOC, OOG...
A80: FAK/ BULLETS | B80: Place of Receipt | C80: POL | D80: POD | E80: Place of Delivery | F80: MODE | G80: SDD (Origin; Dest) | H80: Curr | I80: 20 | J80: 40 | K80: H40 | L80: H45 | M80: Eq type (OT, FR…) | N80: OOG | O80: Shipper own | P80: Hazardous | Q80: OT | R80: FR | Z80: Effective date | AA80: Expiration Date | AB80: Note | AC80: IPI Construction
N81: IG (In gauge) OOG (Out Of Gauge) | O81: SOC COC | P81: Yes / No | Q81: Appl/ Not Appl | R81: Appl/ Not Appl
A89: ORIGIN ARBITRARY TABLE
A90: Rates in USD unless otherwise specified.
A91: APPLICATION FIELD | C91: APPLICABLE FOR FAK U.O.S - ANY BULLET EXCEPTIONS TO BE STATED IN THE 'BULLET EXCEPTIONS' COLUMN
A92: For Place of Receipt indicate origin of cargo
A93: For Place of Intermodal Receipt indicate point and state. Mode: RAIL=R (RAMP), MOTOR=M, RAIL/MOTOR=RM, FEEDER=CY, BARGE=B, RAIL/BARGE=RB (RAMP), BARGE/MOTOR=BM
A94: Where mode = CY, the port listed in the POL/POD column is a placeholder used for internal systems purposes only. The actual POL/POD will be the place of receipt and transshipment locations will vary depending on
A95: the feeder service used without impacting the rate
A97: COUNTRY | B97: Place of Receipt | E97: POL | F97: MODE | G97: SDD (Origin) | H97: Per container | I97: Curr | J97: D20 | K97: D40 | L97: H40 | M97: H45 | N97: Bullet Exceptions | O97: Inland precarriage fuel charge
A98: BANGLADESH | B98: DHAKA | E98: CHITTAGONG | F98: R | G98: N | I98: USD | J98: 270 | K98: 300 | L98: 300 | M98: 380 | N98: FAK BD | O98: Not Applicable
A104: DESTINATION ARBITRARY TABLE
A105: Rates in USD unless otherwise specified.
A106: APPLICATION FIELD | C106: APPLICABLE FOR FAK U.O.S - ANY BULLET EXCEPTIONS TO BE STATED IN THE 'BULLET EXCEPTIONS' COLUMN
A107: For Place of Delivery indicate destination of cargo
A108: For Place of Intermodal Delivery indicate point and state. Mode: RAIL=R (RAMP), MOTOR=M, RAIL/MOTOR=RM, FEEDER=CY, BARGE=B, RAIL/BARGE=RB (RAMP), BARGE/MOTOR=BM
A109: Where mode = CY, the port listed in the POL/POD column is a placeholder used for internal systems purposes only. The actual POL/POD will be the place of receipt and transshipment locations will vary depending on
A110: the feeder service used without impacting the rate
A112: COUNTRY | B112: Place of Delivery | E112: POD | F112: MODE | G112: SDD (Dest) | H112: Per container | I112: Curr | J112: D20 | K112: D40 | L112: H40 | M112: H45 | N112: Bullet Exceptions | O112: Inland oncarriage fuel charge
A118: Note 1
A119: COMMON / GENERAL TARIFF
A120: 1a) | B120: Refer to Boiler Plate for additional rate terms and conditions if any.
A121: 1b) | B121: FAK exclusion as per CMDU tariff 029, Rule 002 Application of Rates and Charges
A123: Note2: | H123: Container type | I123: FAK/ BULLETS | J123: Effective Date | K123: Expiration Date | L123: Applicable Port | M123: Final place of delivery
A124: You must state Applicable, Not applicable. Any amount shown is deemed fixed unless otherwise stated and must be in USD per D40 for each.
A125: General Surcharges valid to all rates unless otherwise specified; list is not exhaustive of all local charges that may apply as per tariff.
A126: BAF | B126: =IF($A126="","",VLOOKUP($A126,Listes!$A$3:$C$230,2,FALSE)) -> Bunker Adjustment Factor | E126: Not Applicable
A127: CFC | B127: =IF($A127="","",VLOOKUP($A127,Listes!$A$3:$C$230,2,FALSE)) -> Cargo Facility Charge | E127: Applicable
A128: Chassis Admin Fee On/C | B128: =IF($A128="","",VLOOKUP($A128,Listes!$A$3:$C$230,2,FALSE)) -> Chassis Administration Fee On-Carriage | E128: Applicable
A129: CPC | B129: =IF($A129="","",VLOOKUP($A129,Listes!$A$3:$C$230,2,FALSE)) -> Chassis Provision Charge | E129: Applicable
A130: CSF | B130: =IF($A130="","",VLOOKUP($A130,Listes!$A$3:$C$230,2,FALSE)) -> Carrier Security Charge | E130: Applicable
A131: CTR Maintenance Dest | B131: =IF($A131="","",VLOOKUP($A131,Listes!$A$3:$C$230,2,FALSE)) -> Container Maintenance Charge Destination | E131: Applicable
A132: DTHC | B132: =IF($A132="","",VLOOKUP($A132,Listes!$A$3:$C$230,2,FALSE)) -> Destination THC / Destination Receiving Charge | E132: Not Applicable
A133: Exp Doc Fee | B133: =IF($A133="","",VLOOKUP($A133,Listes!$A$3:$C$230,2,FALSE)) -> Export Documentation Fees - Carrier | E133: Applicable
A134: Export Declaration | B134: =IF($A134="","",VLOOKUP($A134,Listes!$A$3:$C$230,2,FALSE)) -> Export Declaration Surcharge | E134: Not Applicable
A135: Export Seal Fee | B135: =IF($A135="","",VLOOKUP($A135,Listes!$A$3:$C$230,2,FALSE)) -> Export Seal Fee | E135: Applicable
A136: FR | B136: =IF($A136="","",VLOOKUP($A136,Listes!$A$3:$C$230,2,FALSE)) -> Flat Rack | E136: 800 | H136: 20FR
A137: FR | B137: =IF($A137="","",VLOOKUP($A137,Listes!$A$3:$C$230,2,FALSE)) -> Flat Rack | E137: 1000 | H137: 40FR
A138: GRI | B138: =IF($A138="","",VLOOKUP($A138,Listes!$A$3:$C$230,2,FALSE)) -> General Rate Increase | E138: Applicable
A139: Hazardous fees | B139: =IF($A139="","",VLOOKUP($A139,Listes!$A$3:$C$230,2,FALSE)) -> Hazardous Fees (Ocean) | E139: Applicable
A140: IDDS Onc Additional | B140: =IF($A140="","",VLOOKUP($A140,Listes!$A$3:$C$230,2,FALSE)) -> Oncarriage Additional Intermodal Door Delivery Surcharge | E140: Not Applicable
A141: Inland oncarriage fuel charge | B141: =IF($A141="","",VLOOKUP($A141,Listes!$A$3:$C$230,2,FALSE)) -> Oncarriage Inland Fuel Charge | E141: Not Applicable
A142: Local Port Charge Dest Sanitary Fee | B142: =IF($A142="","",VLOOKUP($A142,Listes!$A$3:$C$230,2,FALSE)) -> Local Port Charge Destination Sanitary Fee | E142: Applicable
A143: Local Port Charge Orig Sanitary Fee | B143: =IF($A143="","",VLOOKUP($A143,Listes!$A$3:$C$230,2,FALSE)) -> Local Port Charge Origin Sanitary Fee | E143: Applicable
A144: O/C EIFS | B144: =IF($A144="","",VLOOKUP($A144,Listes!$A$3:$C$230,2,FALSE)) -> On-Carriage Emergency Inland Fuel Surcharge | E144: Not Applicable
A145: On-Carriage Emergency Surcharge | B145: =IF($A145="","",VLOOKUP($A145,Listes!$A$3:$C$230,2,FALSE)) -> On-Carriage Emergency Intermodal Surcharge | E145: Not Applicable
A146: Oncarriage Hazardous Charge | B146: =IF($A146="","",VLOOKUP($A146,Listes!$A$3:$C$230,2,FALSE)) -> Inland Hazardous Charge Oncarriage | E146: Applicable
A147: OT | B147: =IF($A147="","",VLOOKUP($A147,Listes!$A$3:$C$230,2,FALSE)) -> Open Top | E147: 800 | H147: 20OT
A148: OT | B148: =IF($A148="","",VLOOKUP($A148,Listes!$A$3:$C$230,2,FALSE)) -> Open Top | E148: 1000 | H148: 40OT
...

Sheet APPENDIX F-2 ISC-USWC
A1: Service Contract: | C1: =Cover!B1 -> 25-3117
A2: TERM 6
A3: Amendment Number: | C3: =Cover!B2 -> 58
A4: Merchant Name: | C4: =Cover!B7 -> LOGISTIQUE PRIME FREIGHT INC
A5: Appendix: | C5: F-2
A6: Trade Service: | C6: INBOUND (INDIAN SUB. CONTINENT-USA WC ) (TPX)
A7: TARIFF applicability | C7: CMDU#029 F2
A9: 43 | B9: INB
A11: COMMODITY INDEX
A12: - Unless otherwise indicated, excludes temperature controlled cargo, hazardous cargo, cargo requiring special handling and/or equipment, overweight containers.
A13: FAK/Bullets | B13: Description | J13: Named Account | L13: Partner Code | N13: ALL
A14: FAK | B14: FAK | N14: =IF($A14>0,$A14,"") -> FAK
N15: =IF($A15>0,$A15,"")
N16: =IF($A16>0,$A16,"")
N17: =IF($A17>0,$A17,"")
N18: =IF($A18>0,$A18,"")
A19: Port Group Codes
A20: Port Group Codes | B20: Description
A21: LAX-LGB | B21: LOS ANGELES, LONG BEACH
A26: RATES CONDITIONS
A27: Rates in USD unless otherwise specified. Surcharges listed per line item are exceptions to Note 2 applicability.
A28: For Place of Receipt indicate origin of cargo
A29: For Place of Intermodal Delivery indicate point and state. Mode: PORT=CY, RAIL=R (RAMP), MOTOR=M , RAIL/MOTOR=RM , BARGE=B, RAIL/BARGE=RB (RAMP), MOTOR/BARGE=BM
A30: FAK/ BULLETS | B30: Place of Receipt | C30: POL | D30: POD | E30: Place of Delivery | F30: MODE | G30: SDD (Origin; Dest) | H30: Curr | I30: D20 | J30: D40 | K30: H40 | L30: H45 | M30: OTHC | X30: Effective date | Y30: Expiration Date | Z30: Note | AA30: IPI Construction
M31: Appl/ Not Appl
A32: FAK | C32: KOLKATA(CALCUTTA) | D32: LAX-LGB | F32: CY/CY | G32: N/N | H32: USD | I32: 1600 | J32: 2000 | K32: 2000 | L32: 2530 | Z32: 1,2,4 | AA32: E
A33: FAK | C33: CHENNAI | D33: LAX-LGB | F33: CY/CY | G33: N/N | H33: USD | I33: 1520 | J33: 1900 | K33: 1900 | L33: 2405 | Z33: 1,2,4 | AA33: E
A34: FAK | C34: CHITTAGONG | D34: LAX-LGB | F34: CY/CY | G34: N/N | H34: USD | I34: 1760 | J34: 2200 | K34: 2200 | L34: 2785 | M34: Not Applicable | Z34: 1,2,4 | AA34: E
A35: FAK | C35: COCHIN | D35: LAX-LGB | F35: CY/CY | G35: N/N | H35: USD | I35: 1730 | J35: 2160 | K35: 2160 | L35: 2735 | Z35: 1,2,4 | AA35: E
A36: FAK | C36: COLOMBO | D36: LAX-LGB | F36: CY/CY | G36: N/N | H36: USD | I36: 1680 | J36: 2100 | K36: 2100 | L36: 2660 | Z36: 1,2,4 | AA36: E
A37: FAK | B37: DHAKA | C37: CHITTAGONG | D37: LAX-LGB | F37: R/CY | G37: N/N | H37: USD | I37: 2000 | J37: 2500 | K37: 2500 | L37: 3165 | M37: Not Applicable | Z37: 1,2,4 | AA37: E
A38: FAK | C38: HALDIA | D38: LAX-LGB | F38: CY/CY | G38: N/N | H38: USD | I38: 1680 | J38: 2100 | K38: 2100 | L38: 2660 | Z38: 1,2,4 | AA38: E
A39: FAK | C39: HAZIRA | D39: LAX-LGB | F39: CY/CY | G39: N/N | H39: USD | I39: 1520 | J39: 1900 | K39: 1900 | L39: 2405 | Z39: 1,2,4 | AA39: E
A40: FAK | C40: KARACHI | D40: LAX-LGB | F40: CY/CY | G40: N/N | H40: USD | I40: 1520 | J40: 1900 | K40: 1900 | L40: 2405 | Z40: 1,2,4 | AA40: E
A41: FAK | C41: KRISHNAPATNAM | D41: LAX-LGB | F41: CY/CY | G41: N/N | H41: USD | I41: 1680 | J41: 2100 | K41: 2100 | L41: 2660 | Z41: 1,2,4 | AA41: E
A42: FAK | C42: MANGALORE | D42: LAX-LGB | F42: CY/CY | G42: N/N | H42: USD | I42: 1600 | J42: 2000 | K42: 2000 | L42: 2530 | Z42: 1,2,4 | AA42: E
A43: FAK | C43: MUNDRA | D43: LAX-LGB | F43: CY/CY | G43: N/N | H43: USD | I43: 1520 | J43: 1900 | K43: 1900 | L43: 2405 | Z43: 1,2,4 | AA43: E
A44: FAK | C44: NHAVA SHEVA | D44: LAX-LGB | F44: CY/CY | G44: N/N | H44: USD | I44: 1520 | J44: 1900 | K44: 1900 | L44: 2405 | Z44: 1,2,4 | AA44: E
A45: FAK | C45: PIPAVAV | D45: LAX-LGB | F45: CY/CY | G45: N/N | H45: USD | I45: 1520 | J45: 1900 | K45: 1900 | L45: 2405 | Z45: 1,2,4 | AA45: E
A46: FAK | C46: TUTICORIN | D46: LAX-LGB | F46: CY/CY | G46: N/N | H46: USD | I46: 1520 | J46: 1900 | K46: 1900 | L46: 2405 | Z46: 1,2,4 | AA46: E
A47: FAK | C47: VISAKHAPATNAM | D47: LAX-LGB | F47: CY/CY | G47: N/N | H47: USD | I47: 1520 | J47: 1900 | K47: 1900 | L47: 2405 | Z47: 1,2,4 | AA47: E
A48: FAK | C48: KOLKATA(CALCUTTA) | D48: OAKLAND, CA | F48: CY/CY | G48: N/N | H48: USD | I48: 1600 | J48: 2000 | K48: 2000 | L48: 2530 | Z48: 1,2,4 | AA48: E
A49: FAK | C49: CHENNAI | D49: OAKLAND, CA | F49: CY/CY | G49: N/N | H49: USD | I49: 1520 | J49: 1900 | K49: 1900 | L49: 2405 | Z49: 1,2,4 | AA49: E
A50: FAK | C50: CHITTAGONG | D50: OAKLAND, CA | F50: CY/CY | G50: N/N | H50: USD | I50: 1760 | J50: 2200 | K50: 2200 | L50: 2785 | M50: Not Applicable | Z50: 1,2,4 | AA50: E
A51: FAK | C51: COCHIN | D51: OAKLAND, CA | F51: CY/CY | G51: N/N | H51: USD | I51: 1730 | J51: 2160 | K51: 2160 | L51: 2735 | Z51: 1,2,4 | AA51: E
A52: FAK | C52: COLOMBO | D52: OAKLAND, CA | F52: CY/CY | G52: N/N | H52: USD | I52: 1680 | J52: 2100 | K52: 2100 | L52: 2660 | Z52: 1,2,4 | AA52: E
A53: FAK | B53: DHAKA | C53: CHITTAGONG | D53: OAKLAND, CA | F53: R/CY | G53: N/N | H53: USD | I53: 2000 | J53: 2500 | K53: 2500 | L53: 3165 | M53: Not Applicable | Z53: 1,2,4 | AA53: E
A54: FAK | C54: HALDIA | D54: OAKLAND, CA | F54: CY/CY | G54: N/N | H54: USD | I54: 1680 | J54: 2100 | K54: 2100 | L54: 2660 | Z54: 1,2,4 | AA54: E
A55: FAK | C55: HAZIRA | D55: OAKLAND, CA | F55: CY/CY | G55: N/N | H55: USD | I55: 1520 | J55: 1900 | K55: 1900 | L55: 2405 | Z55: 1,2,4 | AA55: E
A56: FAK | C56: KARACHI | D56: OAKLAND, CA | F56: CY/CY | G56: N/N | H56: USD | I56: 1520 | J56: 1900 | K56: 1900 | L56: 2405 | Z56: 1,2,4 | AA56: E
A57: FAK | C57: KRISHNAPATNAM | D57: OAKLAND, CA | F57: CY/CY | G57: N/N | H57: USD | I57: 1680 | J57: 2100 | K57: 2100 | L57: 2660 | Z57: 1,2,4 | AA57: E
A58: FAK | C58: MANGALORE | D58: OAKLAND, CA | F58: CY/CY | G58: N/N | H58: USD | I58: 1600 | J58: 2000 | K58: 2000 | L58: 2530 | Z58: 1,2,4 | AA58: E
A59: FAK | C59: MUNDRA | D59: OAKLAND, CA | F59: CY/CY | G59: N/N | H59: USD | I59: 1520 | J59: 1900 | K59: 1900 | L59: 2405 | Z59: 1,2,4 | AA59: E
A60: FAK | C60: NHAVA SHEVA | D60: OAKLAND, CA | F60: CY/CY | G60: N/N | H60: USD | I60: 1520 | J60: 1900 | K60: 1900 | L60: 2405 | Z60: 1,2,4 | AA60: E
A61: FAK | C61: PIPAVAV | D61: OAKLAND, CA | F61: CY/CY | G61: N/N | H61: USD | I61: 1520 | J61: 1900 | K61: 1900 | L61: 2405 | Z61: 1,2,4 | AA61: E
A62: FAK | C62: TUTICORIN | D62: OAKLAND, CA | F62: CY/CY | G62: N/N | H62: USD | I62: 1520 | J62: 1900 | K62: 1900 | L62: 2405 | Z62: 1,2,4 | AA62: E
A63: FAK | C63: VISAKHAPATNAM | D63: OAKLAND, CA | F63: CY/CY | G63: N/N | H63: USD | I63: 1520 | J63: 1900 | K63: 1900 | L63: 2405 | Z63: 1,2,4 | AA63: E
A64: FAK | C64: KOLKATA(CALCUTTA) | D64: LAX-LGB | E64: DENVER, CO | F64: CY/R | G64: N/N | H64: USD | I64: 3440 | J64: 4300 | K64: 4300 | L64: 5445 | Z64: 1,2,4 | AA64: E
A65: FAK | C65: CHENNAI | D65: LAX-LGB | E65: DENVER, CO | F65: CY/R | G65: N/N | H65: USD | I65: 3280 | J65: 4100 | K65: 4100 | L65: 5190 | Z65: 1,2,4 | AA65: E
A66: FAK | C66: CHITTAGONG | D66: LAX-LGB | E66: DENVER, CO | F66: CY/R | G66: N/N | H66: USD | I66: 3430 | J66: 4290 | K66: 4290 | L66: 5430 | M66: Not Applicable | Z66: 1,2,4 | AA66: E
A67: FAK | C67: COCHIN | D67: LAX-LGB | E67: DENVER, CO | F67: CY/R | G67: N/N | H67: USD | I67: 3480 | J67: 4350 | K67: 4350 | L67: 5505 | Z67: 1,2,4 | AA67: E
A68: FAK | C68: COLOMBO | D68: LAX-LGB | E68: DENVER, CO | F68: CY/R | G68: N/N | H68: USD | I68: 3600 | J68: 4500 | K68: 4500 | L68: 5695 | Z68: 1,2,4 | AA68: E
A69: FAK | B69: DHAKA | C69: CHITTAGONG | D69: LAX-LGB | E69: DENVER, CO | F69: R/R | G69: N/N | H69: USD | I69: 3670 | J69: 4590 | K69: 4590 | L69: 5810 | M69: Not Applicable | Z69: 1,2,4 | AA69: E
A70: FAK | C70: HALDIA | D70: LAX-LGB | E70: DENVER, CO | F70: CY/R | G70: N/N | H70: USD | I70: 3440 | J70: 4300 | K70: 4300 | L70: 5445 | Z70: 1,2,4 | AA70: E
A71: FAK | C71: HAZIRA | D71: LAX-LGB | E71: DENVER, CO | F71: CY/R | G71: N/N | H71: USD | I71: 3280 | J71: 4100 | K71: 4100 | L71: 5190 | Z71: 1,2,4 | AA71: E
A72: FAK | C72: KARACHI | D72: LAX-LGB | E72: DENVER, CO | F72: CY/R | G72: N/N | H72: USD | I72: 2960 | J72: 3700 | K72: 3700 | L72: 4685 | Z72: 1,2,4 | AA72: E
A73: FAK | C73: KRISHNAPATNAM | D73: LAX-LGB | E73: DENVER, CO | F73: CY/R | G73: N/N | H73: USD | I73: 3480 | J73: 4350 | K73: 4350 | L73: 5505 | Z73: 1,2,4 | AA73: E
A74: FAK | C74: MANGALORE | D74: LAX-LGB | E74: DENVER, CO | F74: CY/R | G74: N/N | H74: USD | I74: 3520 | J74: 4400 | K74: 4400 | L74: 5570 | Z74: 1,2,4 | AA74: E
A75: FAK | C75: MUNDRA | D75: LAX-LGB | E75: DENVER, CO | F75: CY/R | G75: N/N | H75: USD | I75: 3280 | J75: 4100 | K75: 4100 | L75: 5190 | Z75: 1,2,4 | AA75: E
A76: FAK | C76: NHAVA SHEVA | D76: LAX-LGB | E76: DENVER, CO | F76: CY/R | G76: N/N | H76: USD | I76: 3280 | J76: 4100 | K76: 4100 | L76: 5190 | Z76: 1,2,4 | AA76: E
A77: FAK | C77: PIPAVAV | D77: LAX-LGB | E77: DENVER, CO | F77: CY/R | G77: N/N | H77: USD | I77: 3360 | J77: 4200 | K77: 4200 | L77: 5315 | Z77: 1,2,4 | AA77: E
A78: FAK | C78: TUTICORIN | D78: LAX-LGB | E78: DENVER, CO | F78: CY/R | G78: N/N | H78: USD | I78: 3375 | J78: 4220 | K78: 4220 | L78: 5345 | Z78: 1,2,4 | AA78: E
A79: FAK | C79: VISAKHAPATNAM | D79: LAX-LGB | E79: DENVER, CO | F79: CY/R | G79: N/N | H79: USD | I79: 3240 | J79: 4050 | K79: 4050 | L79: 5125 | Z79: 1,2,4 | AA79: E
A80: FAK | C80: KOLKATA(CALCUTTA) | D80: LAX-LGB | E80: EL PASO, TX | F80: CY/R | G80: N/N | H80: USD | I80: 3120 | J80: 3900 | K80: 3900 | L80: 4935 | Z80: 1,2,4 | AA80: E
A81: FAK | C81: CHENNAI | D81: LAX-LGB | E81: EL PASO, TX | F81: CY/R | G81: N/N | H81: USD | I81: 3120 | J81: 3900 | K81: 3900 | L81: 4935 | Z81: 1,2,4 | AA81: E
A82: FAK | C82: CHITTAGONG | D82: LAX-LGB | E82: EL PASO, TX | F82: CY/R | G82: N/N | H82: USD | I82: 3110 | J82: 3890 | K82: 3890 | L82: 4925 | M82: Not Applicable | Z82: 1,2,4 | AA82: E
A83: FAK | C83: COCHIN | D83: LAX-LGB | E83: EL PASO, TX | F83: CY/R | G83: N/N | H83: USD | I83: 3200 | J83: 4000 | K83: 4000 | L83: 5065 | Z83: 1,2,4 | AA83: E
A84: FAK | C84: COLOMBO | D84: LAX-LGB | E84: EL PASO, TX | F84: CY/R | G84: N/N | H84: USD | I84: 3280 | J84: 4100 | K84: 4100 | L84: 5190 | Z84: 1,2,4 | AA84: E
A85: FAK | B85: DHAKA | C85: CHITTAGONG | D85: LAX-LGB | E85: EL PASO, TX | F85: R/R | G85: N/N | H85: USD | I85: 3350 | J85: 4190 | K85: 4190 | L85: 5305 | M85: Not Applicable | Z85: 1,2,4 | AA85: E
A86: FAK | C86: HALDIA | D86: LAX-LGB | E86: EL PASO, TX | F86: CY/R | G86: N/N | H86: USD | I86: 3120 | J86: 3900 | K86: 3900 | L86: 4935 | Z86: 1,2,4 | AA86: E
A87: FAK | C87: HAZIRA | D87: LAX-LGB | E87: EL PASO, TX | F87: CY/R | G87: N/N | H87: USD | I87: 3120 | J87: 3900 | K87: 3900 | L87: 4935 | Z87: 1,2,4 | AA87: E
A88: FAK | C88: KARACHI | D88: LAX-LGB | E88: EL PASO, TX | F88: CY/R | G88: N/N | H88: USD | I88: 2440 | J88: 3050 | K88: 3050 | L88: 3860 | Z88: 1,2,4 | AA88: E
A89: FAK | C89: KRISHNAPATNAM | D89: LAX-LGB | E89: EL PASO, TX | F89: CY/R | G89: N/N | H89: USD | I89: 3160 | J89: 3950 | K89: 3950 | L89: 5000 | Z89: 1,2,4 | AA89: E
A90: FAK | C90: MANGALORE | D90: LAX-LGB | E90: EL PASO, TX | F90: CY/R | G90: N/N | H90: USD | I90: 3240 | J90: 4050 | K90: 4050 | L90: 5125 | Z90: 1,2,4 | AA90: E
A91: FAK | C91: MUNDRA | D91: LAX-LGB | E91: EL PASO, TX | F91: CY/R | G91: N/N | H91: USD | I91: 3120 | J91: 3900 | K91: 3900 | L91: 4935 | Z91: 1,2,4 | AA91: E
A92: FAK | C92: NHAVA SHEVA | D92: LAX-LGB | E92: EL PASO, TX | F92: CY/R | G92: N/N | H92: USD | I92: 3120 | J92: 3900 | K92: 3900 | L92: 4935 | Z92: 1,2,4 | AA92: E
A93: FAK | C93: PIPAVAV | D93: LAX-LGB | E93: EL PASO, TX | F93: CY/R | G93: N/N | H93: USD | I93: 3120 | J93: 3900 | K93: 3900 | L93: 4935 | Z93: 1,2,4 | AA93: E
A94: FAK | C94: TUTICORIN | D94: LAX-LGB | E94: EL PASO, TX | F94: CY/R | G94: N/N | H94: USD | I94: 3120 | J94: 3900 | K94: 3900 | L94: 4935 | Z94: 1,2,4 | AA94: E
A95: FAK | C95: VISAKHAPATNAM | D95: LAX-LGB | E95: EL PASO, TX | F95: CY/R | G95: N/N | H95: USD | I95: 3120 | J95: 3900 | K95: 3900 | L95: 4935 | Z95: 1,2,4 | AA95: E
A96: FAK | C96: KOLKATA(CALCUTTA) | D96: LAX-LGB | E96: ST LOUIS, MO | F96: CY/R | G96: N/N | H96: USD | I96: 3720 | J96: 4650 | K96: 4650 | L96: 5885 | Z96: 1,2,4 | AA96: E
A97: FAK | C97: CHENNAI | D97: LAX-LGB | E97: ST LOUIS, MO | F97: CY/R | G97: N/N | H97: USD | I97: 3745 | J97: 4680 | K97: 4680 | L97: 5925 | Z97: 1,2,4 | AA97: E
A98: FAK | C98: CHITTAGONG | D98: LAX-LGB | E98: ST LOUIS, MO | F98: CY/R | G98: N/N | H98: USD | I98: 3670 | J98: 4590 | K98: 4590 | L98: 5810 | M98: Not Applicable | Z98: 1,2,4 | AA98: E
A99: FAK | C99: COCHIN | D99: LAX-LGB | E99: ST LOUIS, MO | F99: CY/R | G99: N/N | H99: USD | I99: 3720 | J99: 4650 | K99: 4650 | L99: 5885 | Z99: 1,2,4 | AA99: E
A100: FAK | C100: COLOMBO | D100: LAX-LGB | E100: ST LOUIS, MO | F100: CY/R | G100: N/N | H100: USD | I100: 3760 | J100: 4700 | K100: 4700 | L100: 5950 | Z100: 1,2,4 | AA100: E
A101: FAK | B101: DHAKA | C101: CHITTAGONG | D101: LAX-LGB | E101: ST LOUIS, MO | F101: R/R | G101: N/N | H101: USD | I101: 3910 | J101: 4890 | K101: 4890 | L101: 6190 | M101: Not Applicable | Z101: 1,2,4 | AA101: E
A102: FAK | C102: HALDIA | D102: LAX-LGB | E102: ST LOUIS, MO | F102: CY/R | G102: N/N | H102: USD | I102: 3720 | J102: 4650 | K102: 4650 | L102: 5885 | Z102: 1,2,4 | AA102: E
A103: FAK | C103: HAZIRA | D103: LAX-LGB | E103: ST LOUIS, MO | F103: CY/R | G103: N/N | H103: USD | I103: 3680 | J103: 4600 | K103: 4600 | L103: 5825 | Z103: 1,2,4 | AA103: E
A104: FAK | C104: KARACHI | D104: LAX-LGB | E104: ST LOUIS, MO | F104: CY/R | G104: N/N | H104: USD | I104: 3600 | J104: 4500 | K104: 4500 | L104: 5695 | Z104: 1,2,4 | AA104: E
A105: FAK | C105: KRISHNAPATNAM | D105: LAX-LGB | E105: ST LOUIS, MO | F105: CY/R | G105: N/N | H105: USD | I105: 3720 | J105: 4650 | K105: 4650 | L105: 5885 | Z105: 1,2,4 | AA105: E
A106: FAK | C106: MANGALORE | D106: LAX-LGB | E106: ST LOUIS, MO | F106: CY/R | G106: N/N | H106: USD | I106: 3520 | J106: 4400 | K106: 4400 | L106: 5570 | Z106: 1,2,4 | AA106: E
...

Sheet Affiliates
A1: Service Contract: | B1: =Cover!B1 -> 25-3117 | I1: 21
A2: TERM 3
A3: Amendment Number: | B3: =Cover!B2 -> 58
A4: Merchant Name: | B4: =Cover!B7 -> LOGISTIQUE PRIME FREIGHT INC
A5: Appendix: | B5: =Cover!C62 -> Affiliates
A6: 41
A7: LIST OF AFFILIATES / SHIPPER ASSOCIATION MEMBERS
A8: Signatory certifies that they have an ownership interest in all named affiliates. | G8: For NVOCC Affiliates
A9: Partner Code | B9: Name | C9: Street Address | D9: City | E9: State & Zip Code | F9: Country | G9: NVOCC Bond Number
A10: 0006023501 | B10: UNIQUE LOGISTICS INTERNATIONAL (NYC), , LOS ANGELES | C10: 10810 PAINTER AVENUE SANTA FE | D10: LOS ANGELES | E10: SPRINGS, CA 90670 | F10: US

Sheet Listes
A1: Template INBOUND OUTBOUND | B1: V41
A2: Charges | D2: Prepaid/collect | E2: Text / Calc | F2: Level of calc | H2: Exception Charges
A3: 10% CO2 Reduction | B3: 10% CO2 Reduction | C3: ENV06 | D3: Prepaid | E3: Calc | F3: Cargo | H3: 10% CO2 Reduction
A4: 25% CO2 Reduction | B4: 25% CO2 Reduction | C4: ENV02 | D4: Prepaid | E4: Calc | F4: Cargo | H4: 25% CO2 Reduction
A5: 50% CO2 Reduction | B5: 50% CO2 Reduction | C5: ENV10 | D5: Prepaid | E5: Calc | F5: Cargo | H5: 50% CO2 Reduction
A6: 83% CO2 Reduction | B6: 83% CO2 Reduction | C6: ENV04 | D6: Prepaid | E6: Calc | F6: Cargo | H6: 83% CO2 Reduction
A7: ACS Export | B7: Alameda Corridor Surcharge export | C7: CAR12 | D7: Prepaid | E7: Calc | F7: Cargo | H7: ACS Export
A8: ACS Import | B8: Alameda Corridor Surcharge import | C8: CAR10 | D8: Prepaid | E8: Calc | F8: Cargo | H8: ACS Import
A9: Alcohol Surcharge, Oncarriage | B9: On Carriage, Alcohol Surcharge | C9: CAR64 | D9: Collect | E9: Calc | F9: Cargo | H9: Alcohol Surcharge, Oncarriage
A10: Alcohol Surcharge, Precarriage | B10: Pre Carriage, Alcohol Surcharge | C10: CAR14 | D10: Prepaid | E10: Calc | F10: Cargo | H10: Alcohol Surcharge, Precarriage
A11: Atmosphere Control | B11: Atmosphere Control Transport Unit Charge | C11: FRT12 | D11: Prepaid | E11: Calc | F11: Cargo | H11: Atmosphere Control
A12: BAF | B12: Bunker Adjustment Factor | C12: BAF03 | D12: Prepaid | E12: Calc | F12: Cargo | H12: BAF
A13: Bar Lock Security Device | B13: Bar Lock Security Device | C13: SEA07 | D13: Prepaid | E13: Calc | F13: Cargo | H13: Bar Lock Security Device
A14: Benin Freight Tax | B14: Benin Freight Tax | C14: TAX08 | D14: Prepaid | E14: Calc | F14: Cargo | H14: Benin Freight Tax
... A123: Nigerian Freight Tax | B123: Nigerian Freight Tax | C123: TAX09 | D123: Prepaid | E123: Calc | F123: Cargo | H123: Nigerian Freight Tax
A124: NMSA | B124: National Maritime Safety Surcharge | C124: PNG01 | E124: Calc | F124: Cargo | H124: NMSA
A125: O/C EIFS | B125: On-Carriage Emergency Inland Fuel Surcharge | C125: CAR97 | D125: Prepaid | E125: Calc | F125: Cargo | H125: O/C EIFS
A126: O/C Exp Rail | B126: On-Carriage Expedited Rail | C126: CAR84 | D126: Collect | E126: Calc | F126: Cargo | H126: O/C Exp Rail
A127: O/C Haulage | B127: On-Carriage Haulage | C127: CAR50 | D127: Collect | E127: Calc | F127: Cargo | H127: O/C Haulage
A128: O/C Pre Pull VAS CAR PRIME | B128: On-Carriage Pre-Pull VAS Car Prime | C128: CAR61 | D128: Collect | E128: Calc | F128: Cargo | H128: O/C Pre Pull VAS CAR PRIME
A129: O/C Sealing GPS | B129: On Carriage Sealing GPS additional | C129: CAR98 | D129: Collect | E129: Calc | F129: Cargo | H129: O/C Sealing GPS
A130: OC Multi Stop | B130: On Carriage Multistop | C130: CAR52 | D130: Collect | E130: Calc | F130: Cargo | H130: OC Multistop
A131: Off Dock | B131: Off Dock Surcharge | C131: TAX28 | D131: Collect | E131: Calc | F131: Cargo | H131: Off Dock
A132: Oncarriage Barge | B132: OnCarriage Barge - Congestion | C132: CAR54 | D132: Collect | E132: Calc | F132: Cargo | H132: OnCarriage Barge
A133: Oncarriage Congestion | B133: OnCarriage Congestion | C133: CAR81 | D133: Collect | E133: Calc | F133: Cargo | H133: OnCarriage Congestion
A134: On-Carriage Emergency Surcharge | B134: On-Carriage Emergency Intermodal Surcharge | C134: CAR96 | D134: Prepaid | E134: Calc | F134: Cargo | H134: OnCarriage Emergency Intermodal
A135: Oncarriage Hazardous Charge | B135: Inland Hazardous Charge Oncarriage | C135: CAR65 | D135: Collect | E135: Calc | F135: Cargo | H135: Oncarriage Hazardous Charge
A136: Oncarriage Ramp | B136: On-Carriage to Ramp | C136: CAR55 | D136: Collect | E136: Calc | F136: Cargo | H136: Oncarriage Ramp
... A229: X-Ray, Carrier | B229: Scanning by Customs, incl other examinations, carrier | C229: CUS70 | D229: Prepaid | E229: Calc | F229: Cargo | H229: X-Ray, Carrier
A230: GRI | B230: General Rate Increase | C230: GRI general | D230: Prepaid | E230: Calc | F230: Cargo
B233: SDD
B234: N/N
B235: Y/N
B236: Y/Y
B237: N/Y
B243: DRY
B244: Container
B245: Appl/ Not Appl
B246: Per B/L
B247: Per Cargo
B248: Per Container
B249: Per D20
... B396: VT
B397: 53
B399: MQC Type
B401: Global
B402: Sub
B404: Shipper Cert
B406: YES
B409: Charge Automation
B410: Applicable
B411: Not Applicable
B414: GRI/PSS EQ
B415: BK
B416: FR
B417: HA
... B618: ZWD - Zimbabwe Dollar

Sheet SOF BR
A1: Signature on File / Bond Rider
